{
"meta":{"test_sets":[],"test_metrics":[],"learn_metrics":[{"best_value":"Min","name":"RMSE"}],"launch_mode":"Train","parameters":"","iteration_count":1000,"learn_sets":["learn"],"name":"experiment"},
"iterations":[
{"learn":[14.9127897],"iteration":0,"passed_time":0.05645337088,"remaining_time":56.39691751},
{"learn":[14.8135308],"iteration":1,"passed_time":0.05683926493,"remaining_time":28.3627932},
{"learn":[14.71552767],"iteration":2,"passed_time":0.05713536289,"remaining_time":18.9879856},
{"learn":[14.61408645],"iteration":3,"passed_time":0.05743521103,"remaining_time":14.30136755},
{"learn":[14.51957468],"iteration":4,"passed_time":0.05773280905,"remaining_time":11.488829},
{"learn":[14.42874012],"iteration":5,"passed_time":0.0580254485,"remaining_time":9.612882636},
{"learn":[14.3415246],"iteration":6,"passed_time":0.05831608786,"remaining_time":8.272553606},
{"learn":[14.25698782],"iteration":7,"passed_time":0.05857435061,"remaining_time":7.263219475},
{"learn":[14.16444619],"iteration":8,"passed_time":0.05891165893,"remaining_time":6.486828222},
{"learn":[14.06649289],"iteration":9,"passed_time":0.05919592297,"remaining_time":5.860396374},
{"learn":[13.97154017],"iteration":10,"passed_time":0.05949439604,"remaining_time":5.349087062},
{"learn":[13.88269899],"iteration":11,"passed_time":0.05973994983,"remaining_time":4.918589203},
{"learn":[13.79656232],"iteration":12,"passed_time":0.06005567375,"remaining_time":4.559611538},
{"learn":[13.70813938],"iteration":13,"passed_time":0.06032710382,"remaining_time":4.248751741},
{"learn":[13.61892682],"iteration":14,"passed_time":0.06061961827,"remaining_time":3.980688266},
{"learn":[13.52637441],"iteration":15,"passed_time":0.0609631769,"remaining_time":3.749235379},
{"learn":[13.43624911],"iteration":16,"passed_time":0.06132215296,"remaining_time":3.545863315},
{"learn":[13.35247178],"iteration":17,"passed_time":0.06159933331,"remaining_time":3.360585851},
{"learn":[13.26556337],"iteration":18,"passed_time":0.06187159675,"remaining_time":3.194528232},
{"learn":[13.18188505],"iteration":19,"passed_time":0.06215456906,"remaining_time":3.045573884},
{"learn":[13.11347225],"iteration":20,"passed_time":0.06245845906,"remaining_time":2.911753877},
{"learn":[13.04032099],"iteration":21,"passed_time":0.06272618062,"remaining_time":2.788463847},
{"learn":[12.95319961],"iteration":22,"passed_time":0.06298477672,"remaining_time":2.675483776},
{"learn":[12.8702586],"iteration":23,"passed_time":0.06400995234,"remaining_time":2.603071395},
{"learn":[12.78891644],"iteration":24,"passed_time":0.06436351146,"remaining_time":2.510176947},
{"learn":[12.71417622],"iteration":25,"passed_time":0.06463464985,"remaining_time":2.421313421},
{"learn":[12.6351451],"iteration":26,"passed_time":0.06491258024,"remaining_time":2.339257058},
{"learn":[12.55967174],"iteration":27,"passed_time":0.06522417896,"remaining_time":2.264210784},
{"learn":[12.47873478],"iteration":28,"passed_time":0.06548769197,"remaining_time":2.192708583},
{"learn":[12.4067952],"iteration":29,"passed_time":0.06575453848,"remaining_time":2.126063411},
{"learn":[12.33389757],"iteration":30,"passed_time":0.06601088447,"remaining_time":2.063372486},
{"learn":[12.25550289],"iteration":31,"passed_time":0.06623056199,"remaining_time":2.0034745},
{"learn":[12.18194297],"iteration":32,"passed_time":0.06654378579,"remaining_time":1.949934571},
{"learn":[12.11349676],"iteration":33,"passed_time":0.06680950724,"remaining_time":1.898176},
{"learn":[12.0368928],"iteration":34,"passed_time":0.06713381492,"remaining_time":1.850975183},
{"learn":[11.96797082],"iteration":35,"passed_time":0.06754004331,"remaining_time":1.808572271},
{"learn":[11.89589759],"iteration":36,"passed_time":0.06779484756,"remaining_time":1.76449833},
{"learn":[11.82381299],"iteration":37,"passed_time":0.06811836354,"remaining_time":1.724470151},
{"learn":[11.75179457],"iteration":38,"passed_time":0.06838950193,"remaining_time":1.685187471},
{"learn":[11.67841503],"iteration":39,"passed_time":0.0686798496,"remaining_time":1.64831639},
{"learn":[11.60851553],"iteration":40,"passed_time":0.06895744664,"remaining_time":1.612931496},
{"learn":[11.54731332],"iteration":41,"passed_time":0.06922737663,"remaining_time":1.579043496},
{"learn":[11.47943531],"iteration":42,"passed_time":0.06952980823,"remaining_time":1.547442476},
{"learn":[11.42226959],"iteration":43,"passed_time":0.06975148584,"remaining_time":1.515509556},
{"learn":[11.35795462],"iteration":44,"passed_time":0.07001183203,"remaining_time":1.485806658},
{"learn":[11.29088618],"iteration":45,"passed_time":0.07022880108,"remaining_time":1.456484266},
{"learn":[11.22635734],"iteration":46,"passed_time":0.07054894189,"remaining_time":1.430492375},
{"learn":[11.16618638],"iteration":47,"passed_time":0.07082158035,"remaining_time":1.40462801},
{"learn":[11.10831098],"iteration":48,"passed_time":0.07111113631,"remaining_time":1.380136544},
{"learn":[11.04838888],"iteration":49,"passed_time":0.07135452333,"remaining_time":1.355735943},
{"learn":[10.98660201],"iteration":50,"passed_time":0.07160641077,"remaining_time":1.332440859},
{"learn":[10.92429286],"iteration":51,"passed_time":0.07194230236,"remaining_time":1.311563512},
{"learn":[10.86717729],"iteration":52,"passed_time":0.07218239754,"remaining_time":1.289749632},
{"learn":[10.80371647],"iteration":53,"passed_time":0.07277184332,"remaining_time":1.274854885},
{"learn":[10.74431286],"iteration":54,"passed_time":0.07305856581,"remaining_time":1.255278994},
{"learn":[10.68427459],"iteration":55,"passed_time":0.07327028459,"remaining_time":1.235127655},
{"learn":[10.62713108],"iteration":56,"passed_time":0.07349642076,"remaining_time":1.21591447},
{"learn":[10.56832774],"iteration":57,"passed_time":0.07372243192,"remaining_time":1.197353981},
{"learn":[10.5106423],"iteration":58,"passed_time":0.07393948431,"remaining_time":1.179272114},
{"learn":[10.45953296],"iteration":59,"passed_time":0.07426850055,"remaining_time":1.163539842},
{"learn":[10.40365151],"iteration":60,"passed_time":0.07467631235,"remaining_time":1.14952553},
{"learn":[10.3475546],"iteration":61,"passed_time":0.07491119895,"remaining_time":1.133333945},
{"learn":[10.29465126],"iteration":62,"passed_time":0.07515671108,"remaining_time":1.117806957},
{"learn":[10.23774778],"iteration":63,"passed_time":0.07538209721,"remaining_time":1.102463172},
{"learn":[10.18568485],"iteration":64,"passed_time":0.0756068583,"remaining_time":1.087575577},
{"learn":[10.13038471],"iteration":65,"passed_time":0.07591837369,"remaining_time":1.074360015},
{"learn":[10.0740356],"iteration":66,"passed_time":0.07615505204,"remaining_time":1.060487516},
{"learn":[10.02227541],"iteration":67,"passed_time":0.07636577078,"remaining_time":1.04666027},
{"learn":[9.970593295],"iteration":68,"passed_time":0.07657615617,"remaining_time":1.033223209},
{"learn":[9.91947382],"iteration":69,"passed_time":0.07680079226,"remaining_time":1.020353383},
{"learn":[9.866722467],"iteration":70,"passed_time":0.07701005259,"remaining_time":1.007638575},
{"learn":[9.816754407],"iteration":71,"passed_time":0.07723260525,"remaining_time":0.9954424676},
{"learn":[9.765537844],"iteration":72,"passed_time":0.07746186657,"remaining_time":0.9836595932},
{"learn":[9.718362816],"iteration":73,"passed_time":0.07770642031,"remaining_time":0.9723803406},
{"learn":[9.669391201],"iteration":74,"passed_time":0.07792713954,"remaining_time":0.9611013877},
{"learn":[9.621746972],"iteration":75,"passed_time":0.07815494246,"remaining_time":0.9501995635},
{"learn":[9.572537677],"iteration":76,"passed_time":0.07836941138,"remaining_time":0.939415152},
{"learn":[9.526536128],"iteration":77,"passed_time":0.07860158951,"remaining_time":0.9291110965},
{"learn":[9.48371628],"iteration":78,"passed_time":0.07882168371,"remaining_time":0.9189211481},
{"learn":[9.445491082],"iteration":79,"passed_time":0.07896456577,"remaining_time":0.9080925063},
{"learn":[9.398569124],"iteration":80,"passed_time":0.07921686989,"remaining_time":0.8987691781},
{"learn":[9.354063972],"iteration":81,"passed_time":0.07945446496,"remaining_time":0.8895024248},
{"learn":[9.307098902],"iteration":82,"passed_time":0.0796928934,"remaining_time":0.8804624487},
{"learn":[9.26842072],"iteration":83,"passed_time":0.07993086348,"remaining_time":0.8716270351},
{"learn":[9.221365976],"iteration":84,"passed_time":0.08016374998,"remaining_time":0.862939191},
{"learn":[9.178536688],"iteration":85,"passed_time":0.08040347015,"remaining_time":0.8545206014},
{"learn":[9.138841687],"iteration":86,"passed_time":0.08062602281,"remaining_time":0.8461098715},
{"learn":[9.096537479],"iteration":87,"passed_time":0.080832408,"remaining_time":0.8377176829},
{"learn":[9.056597471],"iteration":88,"passed_time":0.08106091928,"remaining_time":0.8297359266},
{"learn":[9.01490307],"iteration":89,"passed_time":0.0813124317,"remaining_time":0.8221590316},
{"learn":[8.977826531],"iteration":90,"passed_time":0.08154048463,"remaining_time":0.814508797},
{"learn":[8.936753503],"iteration":91,"passed_time":0.0817567453,"remaining_time":0.8069035297},
{"learn":[8.895059295],"iteration":92,"passed_time":0.08204555123,"remaining_time":0.8001646771},
{"learn":[8.861743043],"iteration":93,"passed_time":0.08227456254,"remaining_time":0.7929867411},
{"learn":[8.825223339],"iteration":94,"passed_time":0.0825146994,"remaining_time":0.7860610837},
{"learn":[8.786465359],"iteration":95,"passed_time":0.0827307934,"remaining_time":0.7790483045},
{"learn":[8.746461018],"iteration":96,"passed_time":0.08300755707,"remaining_time":0.7727404539},
{"learn":[8.708916962],"iteration":97,"passed_time":0.08324302703,"remaining_time":0.7661756161},
{"learn":[8.670256098],"iteration":98,"passed_time":0.08346949654,"remaining_time":0.7596567312},
{"learn":[8.632172304],"iteration":99,"passed_time":0.08370513318,"remaining_time":0.7533461986},
{"learn":[8.593616929],"iteration":100,"passed_time":0.08395281208,"remaining_time":0.7472631491},
{"learn":[8.558341384],"iteration":101,"passed_time":0.08421153318,"remaining_time":0.7413917333},
{"learn":[8.52696993],"iteration":102,"passed_time":0.0844393361,"remaining_time":0.7353600435},
{"learn":[8.489976409],"iteration":103,"passed_time":0.08465647182,"remaining_time":0.7293480649},
{"learn":[8.454174938],"iteration":104,"passed_time":0.08487331586,"remaining_time":0.7234439781},
{"learn":[8.416924581],"iteration":105,"passed_time":0.08510470229,"remaining_time":0.7177698476},
{"learn":[8.381466861],"iteration":106,"passed_time":0.08534133897,"remaining_time":0.7122412682},
{"learn":[8.346847622],"iteration":107,"passed_time":0.08557060029,"remaining_time":0.7067497728},
{"learn":[8.314175576],"iteration":108,"passed_time":0.08578086067,"remaining_time":0.7011995125},
{"learn":[8.281770212],"iteration":109,"passed_time":0.08603124804,"remaining_time":0.6960710068},
{"learn":[8.246489425],"iteration":110,"passed_time":0.08624467524,"remaining_time":0.690734381},
{"learn":[8.210759934],"iteration":111,"passed_time":0.08648539546,"remaining_time":0.6857056354},
{"learn":[8.178253689],"iteration":112,"passed_time":0.08670907317,"remaining_time":0.6806278576},
{"learn":[8.14935928],"iteration":113,"passed_time":0.08696146064,"remaining_time":0.6758583695},
{"learn":[8.119869733],"iteration":114,"passed_time":0.08716692911,"remaining_time":0.6708063675},
{"learn":[8.092463517],"iteration":115,"passed_time":0.08739373198,"remaining_time":0.6660005092},
{"learn":[8.06164814],"iteration":116,"passed_time":0.08759161675,"remaining_time":0.6610546803},
{"learn":[8.032883057],"iteration":117,"passed_time":0.08783246198,"remaining_time":0.6565104361},
{"learn":[8.002632059],"iteration":118,"passed_time":0.08805168114,"remaining_time":0.6518784124},
{"learn":[7.969752901],"iteration":119,"passed_time":0.08826590005,"remaining_time":0.647283267},
{"learn":[7.941336118],"iteration":120,"passed_time":0.08849374463,"remaining_time":0.6428595168},
{"learn":[7.911495732],"iteration":121,"passed_time":0.08871354715,"remaining_time":0.6384466754},
{"learn":[7.880662265],"iteration":122,"passed_time":0.08893972498,"remaining_time":0.63414747},
{"learn":[7.851937576],"iteration":123,"passed_time":0.08915865246,"remaining_time":0.6298627384},
{"learn":[7.822725057],"iteration":124,"passed_time":0.08936932953,"remaining_time":0.6255853067},
{"learn":[7.796863107],"iteration":125,"passed_time":0.08959675743,"remaining_time":0.621488619},
{"learn":[7.768178982],"iteration":126,"passed_time":0.08984431132,"remaining_time":0.6175912109},
{"learn":[7.739953674],"iteration":127,"passed_time":0.0900721559,"remaining_time":0.6136165621},
{"learn":[7.71516065],"iteration":128,"passed_time":0.09028512475,"remaining_time":0.6095995632},
{"learn":[7.68924738],"iteration":129,"passed_time":0.09052284482,"remaining_time":0.6058067307},
{"learn":[7.662309868],"iteration":130,"passed_time":0.09075931483,"remaining_time":0.6020598824},
{"learn":[7.638542915],"iteration":131,"passed_time":0.09099761827,"remaining_time":0.5983782777},
{"learn":[7.611173706],"iteration":132,"passed_time":0.09122262938,"remaining_time":0.594661802},
{"learn":[7.588056015],"iteration":133,"passed_time":0.09143688996,"remaining_time":0.5909279605},
{"learn":[7.563073006],"iteration":134,"passed_time":0.09165548408,"remaining_time":0.5872740276},
{"learn":[7.540696684],"iteration":135,"passed_time":0.09178811563,"remaining_time":0.5831244993},
{"learn":[7.515166524],"iteration":136,"passed_time":0.09203341941,"remaining_time":0.5797433646},
{"learn":[7.489213865],"iteration":137,"passed_time":0.09224509653,"remaining_time":0.5761976319},
{"learn":[7.4671567],"iteration":138,"passed_time":0.0924592321,"remaining_time":0.5727150996},
{"learn":[7.443278731],"iteration":139,"passed_time":0.09273978762,"remaining_time":0.5696872668},
{"learn":[7.419159194],"iteration":140,"passed_time":0.09296079854,"remaining_time":0.566335645},
{"learn":[7.395963061],"iteration":141,"passed_time":0.09318489294,"remaining_time":0.5630467475},
{"learn":[7.374921554],"iteration":142,"passed_time":0.09339898684,"remaining_time":0.5597407813},
{"learn":[7.35329762],"iteration":143,"passed_time":0.09363053994,"remaining_time":0.556581543},
{"learn":[7.329195984],"iteration":144,"passed_time":0.09386167635,"remaining_time":0.5534602295},
{"learn":[7.306648601],"iteration":145,"passed_time":0.09411306377,"remaining_time":0.550496962},
{"learn":[7.284603988],"iteration":146,"passed_time":0.09433344965,"remaining_time":0.5473906976},
{"learn":[7.262922602],"iteration":147,"passed_time":0.09454429339,"remaining_time":0.5442684998},
{"learn":[7.240410944],"iteration":148,"passed_time":0.0947543871,"remaining_time":0.5411810968},
{"learn":[7.219014548],"iteration":149,"passed_time":0.09497239787,"remaining_time":0.5381769212},
{"learn":[7.199098585],"iteration":150,"passed_time":0.09522741046,"remaining_time":0.5354176919},
{"learn":[7.179469951],"iteration":151,"passed_time":0.09549104847,"remaining_time":0.5327395336},
{"learn":[7.157723805],"iteration":152,"passed_time":0.09572318494,"remaining_time":0.5299185467},
{"learn":[7.135543815],"iteration":153,"passed_time":0.09595127953,"remaining_time":0.5271089772},
{"learn":[7.113130086],"iteration":154,"passed_time":0.09623383515,"remaining_time":0.5246296174},
{"learn":[7.092866641],"iteration":155,"passed_time":0.0964765138,"remaining_time":0.5219626772},
{"learn":[7.070706823],"iteration":156,"passed_time":0.0967195258,"remaining_time":0.5193284092},
{"learn":[7.049542242],"iteration":157,"passed_time":0.0969739967,"remaining_time":0.5167854761},
{"learn":[7.029749195],"iteration":158,"passed_time":0.09718584049,"remaining_time":0.5140458607},
{"learn":[7.012748292],"iteration":159,"passed_time":0.09731643028,"remaining_time":0.5109112589},
{"learn":[6.992498653],"iteration":160,"passed_time":0.09756085901,"remaining_time":0.5084072094},
{"learn":[6.971514968],"iteration":161,"passed_time":0.09778278664,"remaining_time":0.5058146617},
{"learn":[6.95112065],"iteration":162,"passed_time":0.09801650651,"remaining_time":0.5033117543},
{"learn":[6.936804145],"iteration":163,"passed_time":0.0982295587,"remaining_time":0.5007311651},
{"learn":[6.918483741],"iteration":164,"passed_time":0.09844519434,"remaining_time":0.4981923471},
{"learn":[6.899104772],"iteration":165,"passed_time":0.09865116285,"remaining_time":0.4956329507},
{"learn":[6.88109537],"iteration":166,"passed_time":0.09895838635,"remaining_time":0.4936068014},
{"learn":[6.862065294],"iteration":167,"passed_time":0.09920764866,"remaining_time":0.4913140696},
{"learn":[6.846172347],"iteration":168,"passed_time":0.09945716098,"remaining_time":0.4890467501},
{"learn":[6.827825318],"iteration":169,"passed_time":0.0996830888,"remaining_time":0.4866880218},
{"learn":[6.812280268],"iteration":170,"passed_time":0.09990097456,"remaining_time":0.4843152509},
{"learn":[6.798641759],"iteration":171,"passed_time":0.1001357362,"remaining_time":0.4820487764},
{"learn":[6.781204229],"iteration":172,"passed_time":0.1004118748,"remaining_time":0.4800035864},
{"learn":[6.764758805],"iteration":173,"passed_time":0.1006575953,"remaining_time":0.4778343315},
{"learn":[6.747624968],"iteration":174,"passed_time":0.1009143163,"remaining_time":0.4757389195},
{"learn":[6.731155847],"iteration":175,"passed_time":0.1011832045,"remaining_time":0.4737213667},
{"learn":[6.714120881],"iteration":176,"passed_time":0.1014261332,"remaining_time":0.4716028679},
{"learn":[6.69760595],"iteration":177,"passed_time":0.1016562279,"remaining_time":0.469446176},
{"learn":[6.681652804],"iteration":178,"passed_time":0.1018833641,"remaining_time":0.467297441},
{"learn":[6.668827838],"iteration":179,"passed_time":0.1020872075,"remaining_time":0.4650639453},
{"learn":[6.651982117],"iteration":180,"passed_time":0.1023510539,"remaining_time":0.4631243819},
{"learn":[6.638450641],"iteration":181,"passed_time":0.1026038164,"remaining_time":0.4611534164},
{"learn":[6.623279337],"iteration":182,"passed_time":0.1028587039,"remaining_time":0.4592107165},
{"learn":[6.607003516],"iteration":183,"passed_time":0.1030742563,"remaining_time":0.457111919},
{"learn":[6.59177276],"iteration":184,"passed_time":0.1033196017,"remaining_time":0.4551647318},
{"learn":[6.577733275],"iteration":185,"passed_time":0.1035508214,"remaining_time":0.4531740251},
{"learn":[6.563451067],"iteration":186,"passed_time":0.103784083,"remaining_time":0.4512110131},
{"learn":[6.54858762],"iteration":187,"passed_time":0.10399351,"remaining_time":0.449163458},
{"learn":[6.535014777],"iteration":188,"passed_time":0.1042064372,"remaining_time":0.4471503732},
{"learn":[6.520930744],"iteration":189,"passed_time":0.1044396153,"remaining_time":0.4452425706},
{"learn":[6.508453126],"iteration":190,"passed_time":0.1046767104,"remaining_time":0.4433688937},
{"learn":[6.493562788],"iteration":191,"passed_time":0.104939515,"remaining_time":0.441620459},
{"learn":[6.480684901],"iteration":192,"passed_time":0.1051450252,"remaining_time":0.4396478513},
{"learn":[6.468692901],"iteration":193,"passed_time":0.1053938708,"remaining_time":0.4378735044},
{"learn":[6.454229284],"iteration":194,"passed_time":0.105608173,"remaining_time":0.4359722015},
{"learn":[6.44130333],"iteration":195,"passed_time":0.1058180584,"remaining_time":0.4340699947},
{"learn":[6.429857027],"iteration":196,"passed_time":0.1060551951,"remaining_time":0.4322960491},
{"learn":[6.417005814],"iteration":197,"passed_time":0.1063042491,"remaining_time":0.4305858978},
{"learn":[6.403780912],"iteration":198,"passed_time":0.1065222182,"remaining_time":0.4287653103},
{"learn":[6.39190858],"iteration":199,"passed_time":0.1067221864,"remaining_time":0.4268887455},
{"learn":[6.378189291],"iteration":200,"passed_time":0.1070127007,"remaining_time":0.4253887954},
{"learn":[6.36444611],"iteration":201,"passed_time":0.1072396286,"remaining_time":0.4236496219},
{"learn":[6.352767956],"iteration":202,"passed_time":0.1074605562,"remaining_time":0.4219017895},
{"learn":[6.342224184],"iteration":203,"passed_time":0.1077149854,"remaining_time":0.4202996489},
{"learn":[6.330822459],"iteration":204,"passed_time":0.107949372,"remaining_time":0.4186329303},
{"learn":[6.320152049],"iteration":205,"passed_time":0.1082117599,"remaining_time":0.4170880456},
{"learn":[6.308428586],"iteration":206,"passed_time":0.1084545219,"remaining_time":0.4154803666},
{"learn":[6.297540356],"iteration":207,"passed_time":0.1086894502,"remaining_time":0.4138559834},
{"learn":[6.28629099],"iteration":208,"passed_time":0.1089411709,"remaining_time":0.4123084508},
{"learn":[6.275841374],"iteration":209,"passed_time":0.1091519314,"remaining_time":0.4106191703},
{"learn":[6.264483662],"iteration":210,"passed_time":0.1094208196,"remaining_time":0.4091612639},
{"learn":[6.254533821],"iteration":211,"passed_time":0.1096627899,"remaining_time":0.407614521},
{"learn":[6.24339262],"iteration":212,"passed_time":0.1098854676,"remaining_time":0.4060087464},
{"learn":[6.231009598],"iteration":213,"passed_time":0.1101080619,"remaining_time":0.4044155918},
{"learn":[6.219930013],"iteration":214,"passed_time":0.1103678247,"remaining_time":0.4029708949},
{"learn":[6.208063951],"iteration":215,"passed_time":0.1106138785,"remaining_time":0.401487411},
{"learn":[6.19741683],"iteration":216,"passed_time":0.1108361812,"remaining_time":0.3999296307},
{"learn":[6.187050261],"iteration":217,"passed_time":0.1110497751,"remaining_time":0.3983528628},
{"learn":[6.17531516],"iteration":218,"passed_time":0.1112724111,"remaining_time":0.3968207901},
{"learn":[6.164888099],"iteration":219,"passed_time":0.1114888801,"remaining_time":0.3952787566},
{"learn":[6.154696147],"iteration":220,"passed_time":0.111710266,"remaining_time":0.3937660508},
{"learn":[6.14426803],"iteration":221,"passed_time":0.111925735,"remaining_time":0.3922442424},
{"learn":[6.135221696],"iteration":222,"passed_time":0.112141829,"remaining_time":0.3907363279},
{"learn":[6.124868134],"iteration":223,"passed_time":0.112418926,"remaining_time":0.3894512794},
{"learn":[6.114203388],"iteration":224,"passed_time":0.1126869392,"remaining_time":0.3881439018},
{"learn":[6.103976895],"iteration":225,"passed_time":0.1129296596,"remaining_time":0.3867590995},
{"learn":[6.094238906],"iteration":226,"passed_time":0.1131617543,"remaining_time":0.3853481767},
{"learn":[6.083259792],"iteration":227,"passed_time":0.1134210172,"remaining_time":0.3840395844},
{"learn":[6.073858783],"iteration":228,"passed_time":0.1136385696,"remaining_time":0.3825997255},
{"learn":[6.064932703],"iteration":229,"passed_time":0.1138726228,"remaining_time":0.3812257371},
{"learn":[6.054209735],"iteration":230,"passed_time":0.1141282187,"remaining_time":0.3799333342},
{"learn":[6.047095961],"iteration":231,"passed_time":0.1143521048,"remaining_time":0.3785448986},
{"learn":[6.041890794],"iteration":232,"passed_time":0.1144364423,"remaining_time":0.3767070869},
{"learn":[6.032632521],"iteration":233,"passed_time":0.1146520779,"remaining_time":0.3753140671},
{"learn":[6.022967446],"iteration":234,"passed_time":0.1148778391,"remaining_time":0.3739640294},
{"learn":[6.013867551],"iteration":235,"passed_time":0.1151141841,"remaining_time":0.3726577824},
{"learn":[6.007333054],"iteration":236,"passed_time":0.1153546126,"remaining_time":0.3713737107},
{"learn":[5.998811077],"iteration":237,"passed_time":0.1155817488,"remaining_time":0.3700558513},
{"learn":[5.990632728],"iteration":238,"passed_time":0.1158504704,"remaining_time":0.3688795314},
{"learn":[5.98399256],"iteration":239,"passed_time":0.1160652311,"remaining_time":0.3675398983},
{"learn":[5.975442939],"iteration":240,"passed_time":0.1162819918,"remaining_time":0.3662158993},
{"learn":[5.96774489],"iteration":241,"passed_time":0.1165099197,"remaining_time":0.3649360294},
{"learn":[5.960078847],"iteration":242,"passed_time":0.1168049759,"remaining_time":0.3638739373},
{"learn":[5.951180473],"iteration":243,"passed_time":0.1170657805,"remaining_time":0.3627120083},
{"learn":[5.942486976],"iteration":244,"passed_time":0.1172806661,"remaining_time":0.3614159301},
{"learn":[5.934655867],"iteration":245,"passed_time":0.1175085523,"remaining_time":0.3601684896},
{"learn":[5.926786537],"iteration":246,"passed_time":0.1178319016,"remaining_time":0.3592203317},
{"learn":[5.920856272],"iteration":247,"passed_time":0.1180292447,"remaining_time":0.3578951291},
{"learn":[5.913828545],"iteration":248,"passed_time":0.1182851323,"remaining_time":0.3567555598},
{"learn":[5.905224118],"iteration":249,"passed_time":0.1185303111,"remaining_time":0.3555909333},
{"learn":[5.897022748],"iteration":250,"passed_time":0.1187594474,"remaining_time":0.3543857614},
{"learn":[5.890220444],"iteration":251,"passed_time":0.1189683327,"remaining_time":0.3531282257},
{"learn":[5.88123931],"iteration":252,"passed_time":0.1192185951,"remaining_time":0.3520011483},
{"learn":[5.872794425],"iteration":253,"passed_time":0.1194656073,"remaining_time":0.3508714293},
{"learn":[5.864265149],"iteration":254,"passed_time":0.1197130362,"remaining_time":0.3497498508},
{"learn":[5.85663108],"iteration":255,"passed_time":0.1199565065,"remaining_time":0.3486235971},
{"learn":[5.851049231],"iteration":256,"passed_time":0.1202046438,"remaining_time":0.3475177056},
{"learn":[5.843850613],"iteration":257,"passed_time":0.1204337801,"remaining_time":0.3463638172},
{"learn":[5.836945762],"iteration":258,"passed_time":0.1206763754,"remaining_time":0.345255576},
{"learn":[5.830696806],"iteration":259,"passed_time":0.1208912193,"remaining_time":0.3440750089},
{"learn":[5.82359864],"iteration":260,"passed_time":0.1211371482,"remaining_time":0.3429898563},
{"learn":[5.816610492],"iteration":261,"passed_time":0.1213930775,"remaining_time":0.3419392793},
{"learn":[5.811063116],"iteration":262,"passed_time":0.1216217971,"remaining_time":0.340818496},
{"learn":[5.805268822],"iteration":263,"passed_time":0.1217590539,"remaining_time":0.3394494835},
{"learn":[5.799755793],"iteration":264,"passed_time":0.1219721894,"remaining_time":0.3383002234},
{"learn":[5.793009059],"iteration":265,"passed_time":0.1222063676,"remaining_time":0.337216067},
{"learn":[5.786520923],"iteration":266,"passed_time":0.1223799595,"remaining_time":0.3359719488},
{"learn":[5.780041243],"iteration":267,"passed_time":0.1226281384,"remaining_time":0.3349395423},
{"learn":[5.774018181],"iteration":268,"passed_time":0.1228558997,"remaining_time":0.3338574821},
{"learn":[5.768033121],"iteration":269,"passed_time":0.1230664101,"remaining_time":0.3327351088},
{"learn":[5.761761228],"iteration":270,"passed_time":0.1232878794,"remaining_time":0.3316489448},
{"learn":[5.755610341],"iteration":271,"passed_time":0.1235408502,"remaining_time":0.330653452},
{"learn":[5.751312104],"iteration":272,"passed_time":0.1236566476,"remaining_time":0.3292981054},
{"learn":[5.74544464],"iteration":273,"passed_time":0.1238840338,"remaining_time":0.3282474764},
{"learn":[5.738636421],"iteration":274,"passed_time":0.1241255457,"remaining_time":0.3272400751},
{"learn":[5.732319318],"iteration":275,"passed_time":0.1243751414,"remaining_time":0.3262594288},
{"learn":[5.725791067],"iteration":276,"passed_time":0.1246417379,"remaining_time":0.325328435},
{"learn":[5.720502377],"iteration":277,"passed_time":0.1248992506,"remaining_time":0.3243786292},
{"learn":[5.714925193],"iteration":278,"passed_time":0.1251667221,"remaining_time":0.3234595221},
{"learn":[5.709349888],"iteration":279,"passed_time":0.1253971918,"remaining_time":0.3224499219},
{"learn":[5.703002576],"iteration":280,"passed_time":0.1256504543,"remaining_time":0.3215041875},
{"learn":[5.698065484],"iteration":281,"passed_time":0.1259285097,"remaining_time":0.3206264893},
{"learn":[5.691878337],"iteration":282,"passed_time":0.1261610629,"remaining_time":0.3196377459},
{"learn":[5.687011086],"iteration":283,"passed_time":0.1264194507,"remaining_time":0.3187194601},
{"learn":[5.681701709],"iteration":284,"passed_time":0.1266817553,"remaining_time":0.3178156316},
{"learn":[5.675228111],"iteration":285,"passed_time":0.1269056413,"remaining_time":0.3168203773},
{"learn":[5.67006498],"iteration":286,"passed_time":0.127121777,"remaining_time":0.3158112439},
{"learn":[5.66474822],"iteration":287,"passed_time":0.1273853733,"remaining_time":0.3149249508},
{"learn":[5.659473913],"iteration":288,"passed_time":0.1276340523,"remaining_time":0.3140062671},
{"learn":[5.653253822],"iteration":289,"passed_time":0.1278582717,"remaining_time":0.3130323204},
{"learn":[5.647752652],"iteration":290,"passed_time":0.1281262433,"remaining_time":0.3121701253},
{"learn":[5.643004391],"iteration":291,"passed_time":0.1282919598,"remaining_time":0.3110640669},
{"learn":[5.638118758],"iteration":292,"passed_time":0.1285141374,"remaining_time":0.3101006661},
{"learn":[5.633367751],"iteration":293,"passed_time":0.1287585245,"remaining_time":0.3091956404},
{"learn":[5.627354584],"iteration":294,"passed_time":0.1289818688,"remaining_time":0.3082448052},
{"learn":[5.622599176],"iteration":295,"passed_time":0.1292127136,"remaining_time":0.3073167242},
{"learn":[5.617105405],"iteration":296,"passed_time":0.1294535171,"remaining_time":0.3064169109},
{"learn":[5.612845184],"iteration":297,"passed_time":0.1297069046,"remaining_time":0.3055511646},
{"learn":[5.608179933],"iteration":298,"passed_time":0.1299234153,"remaining_time":0.3046030574},
{"learn":[5.603992679],"iteration":299,"passed_time":0.1301384676,"remaining_time":0.3036564245},
{"learn":[5.598958874],"iteration":300,"passed_time":0.1303814796,"remaining_time":0.3027795822},
{"learn":[5.59389345],"iteration":301,"passed_time":0.1306110326,"remaining_time":0.3018758304},
{"learn":[5.588342081],"iteration":302,"passed_time":0.1308984635,"remaining_time":0.3011096668},
{"learn":[5.58330983],"iteration":303,"passed_time":0.1311476425,"remaining_time":0.3002590761},
{"learn":[5.578551572],"iteration":304,"passed_time":0.1313656949,"remaining_time":0.2993415015},
{"learn":[5.574623415],"iteration":305,"passed_time":0.131597248,"remaining_time":0.298459118},
{"learn":[5.569803613],"iteration":306,"passed_time":0.1318188839,"remaining_time":0.2975585882},
{"learn":[5.565021478],"iteration":307,"passed_time":0.1320259775,"remaining_time":0.2966297936},
{"learn":[5.561025858],"iteration":308,"passed_time":0.1322430299,"remaining_time":0.2957279406},
{"learn":[5.556691574],"iteration":309,"passed_time":0.1325116265,"remaining_time":0.2949452331},
{"learn":[5.55170604],"iteration":310,"passed_time":0.1327762645,"remaining_time":0.294157062},
{"learn":[5.547294577],"iteration":311,"passed_time":0.1329919835,"remaining_time":0.2932643739},
{"learn":[5.541753683],"iteration":312,"passed_time":0.1332225782,"remaining_time":0.2924086622},
{"learn":[5.53721509],"iteration":313,"passed_time":0.1334435058,"remaining_time":0.2915358121},
{"learn":[5.532844808],"iteration":314,"passed_time":0.1336760173,"remaining_time":0.2906922916},
{"learn":[5.528969498],"iteration":315,"passed_time":0.1339141124,"remaining_time":0.2898647243},
{"learn":[5.524587779],"iteration":316,"passed_time":0.1341447904,"remaining_time":0.2890248955},
{"learn":[5.520880304],"iteration":317,"passed_time":0.1343883441,"remaining_time":0.2882165116},
{"learn":[5.517133278],"iteration":318,"passed_time":0.1345920625,"remaining_time":0.2873266288},
{"learn":[5.513136261],"iteration":319,"passed_time":0.1348241573,"remaining_time":0.2865013343},
{"learn":[5.509393446],"iteration":320,"passed_time":0.1350489184,"remaining_time":0.2856642231},
{"learn":[5.505077898],"iteration":321,"passed_time":0.1352820549,"remaining_time":0.2848485505},
{"learn":[5.501490298],"iteration":322,"passed_time":0.135491857,"remaining_time":0.2839875764},
{"learn":[5.496886789],"iteration":323,"passed_time":0.1357022424,"remaining_time":0.283131839},
{"learn":[5.493773807],"iteration":324,"passed_time":0.1359320454,"remaining_time":0.2823204019},
{"learn":[5.490701805],"iteration":325,"passed_time":0.1361293468,"remaining_time":0.2814453366},
{"learn":[5.486140036],"iteration":326,"passed_time":0.1363588164,"remaining_time":0.2806406222},
{"learn":[5.482057338],"iteration":327,"passed_time":0.1366018701,"remaining_time":0.2798672461},
{"learn":[5.478002124],"iteration":328,"passed_time":0.1368397152,"remaining_time":0.2790864708},
{"learn":[5.47694727],"iteration":329,"passed_time":0.1369331781,"remaining_time":0.2780158465},
{"learn":[5.472941813],"iteration":330,"passed_time":0.1371625645,"remaining_time":0.2772258478},
{"learn":[5.469076828],"iteration":331,"passed_time":0.1374216189,"remaining_time":0.27649892},
{"learn":[5.465955128],"iteration":332,"passed_time":0.1376449216,"remaining_time":0.2757031913},
{"learn":[5.462792484],"iteration":333,"passed_time":0.1378710161,"remaining_time":0.2749164573},
{"learn":[5.459473445],"iteration":334,"passed_time":0.1380701509,"remaining_time":0.2740795534},
{"learn":[5.456847362],"iteration":335,"passed_time":0.138288245,"remaining_time":0.2732839128},
{"learn":[5.45368045],"iteration":336,"passed_time":0.1385286319,"remaining_time":0.2725355577},
{"learn":[5.449417302],"iteration":337,"passed_time":0.1387371005,"remaining_time":0.271727694},
{"learn":[5.446103289],"iteration":338,"passed_time":0.1389508194,"remaining_time":0.2709336037},
{"learn":[5.442247687],"iteration":339,"passed_time":0.1391588714,"remaining_time":0.2701319268},
{"learn":[5.43871318],"iteration":340,"passed_time":0.1393927579,"remaining_time":0.2693836583},
{"learn":[5.434387794],"iteration":341,"passed_time":0.1396051017,"remaining_time":0.2685969501},
{"learn":[5.430331476],"iteration":342,"passed_time":0.1398165288,"remaining_time":0.2678118351},
{"learn":[5.427309078],"iteration":343,"passed_time":0.1400249558,"remaining_time":0.2670243343},
{"learn":[5.423101806],"iteration":344,"passed_time":0.1402688428,"remaining_time":0.2663075132},
{"learn":[5.420860485],"iteration":345,"passed_time":0.1404925622,"remaining_time":0.2655553055},
{"learn":[5.417915372],"iteration":346,"passed_time":0.1406921971,"remaining_time":0.2647608204},
{"learn":[5.414995311],"iteration":347,"passed_time":0.1409298755,"remaining_time":0.2640410311},
{"learn":[5.411536052],"iteration":348,"passed_time":0.1411645537,"remaining_time":0.2633184083},
{"learn":[5.408800441],"iteration":349,"passed_time":0.1413898149,"remaining_time":0.2625810847},
{"learn":[5.405299329],"iteration":350,"passed_time":0.1416242848,"remaining_time":0.261863706},
{"learn":[5.402158131],"iteration":351,"passed_time":0.1418470458,"remaining_time":0.2611275161},
{"learn":[5.39950541],"iteration":352,"passed_time":0.1420700568,"remaining_time":0.2603946933},
{"learn":[5.396513947],"iteration":353,"passed_time":0.1422806505,"remaining_time":0.259642091},
{"learn":[5.393482425],"iteration":354,"passed_time":0.1424943277,"remaining_time":0.2588981447},
{"learn":[5.390112004],"iteration":355,"passed_time":0.142722214,"remaining_time":0.2581828815},
{"learn":[5.386559945],"iteration":356,"passed_time":0.1429670594,"remaining_time":0.2575008941},
{"learn":[5.382728426],"iteration":357,"passed_time":0.1431752364,"remaining_time":0.2567555914},
{"learn":[5.380333419],"iteration":358,"passed_time":0.1433959556,"remaining_time":0.2560356756},
{"learn":[5.377356268],"iteration":359,"passed_time":0.1436192583,"remaining_time":0.2553231258},
{"learn":[5.37377165],"iteration":360,"passed_time":0.1438536032,"remaining_time":0.2546328322},
{"learn":[5.371265297],"iteration":361,"passed_time":0.1440751975,"remaining_time":0.2539225856},
{"learn":[5.368459575],"iteration":362,"passed_time":0.1443018753,"remaining_time":0.253223952},
{"learn":[5.364901372],"iteration":363,"passed_time":0.1445251363,"remaining_time":0.2525219415},
{"learn":[5.361414721],"iteration":364,"passed_time":0.1447758571,"remaining_time":0.2518703267},
{"learn":[5.358858927],"iteration":365,"passed_time":0.1450187857,"remaining_time":0.2512074048},
{"learn":[5.356914151],"iteration":366,"passed_time":0.1451799603,"remaining_time":0.2504057627},
{"learn":[5.354301564],"iteration":367,"passed_time":0.1454315144,"remaining_time":0.2497628183},
{"learn":[5.352021742],"iteration":368,"passed_time":0.1456621091,"remaining_time":0.2490861541},
{"learn":[5.348774042],"iteration":369,"passed_time":0.1459191635,"remaining_time":0.2484569541},
{"learn":[5.34568617],"iteration":370,"passed_time":0.1461375076,"remaining_time":0.2477641302},
{"learn":[5.342407664],"iteration":371,"passed_time":0.1463591019,"remaining_time":0.2470793441},
{"learn":[5.339557569],"iteration":372,"passed_time":0.1465654454,"remaining_time":0.2463714056},
{"learn":[5.337039354],"iteration":373,"passed_time":0.1467879564,"remaining_time":0.2456932105},
{"learn":[5.334176686],"iteration":374,"passed_time":0.1469891747,"remaining_time":0.2449819578},
{"learn":[5.330852676],"iteration":375,"passed_time":0.1471983933,"remaining_time":0.2442866953},
{"learn":[5.327342046],"iteration":376,"passed_time":0.147407487,"remaining_time":0.2435938048},
{"learn":[5.32513323],"iteration":377,"passed_time":0.1476293313,"remaining_time":0.2429244552},
{"learn":[5.323215417],"iteration":378,"passed_time":0.1478286745,"remaining_time":0.2422205985},
{"learn":[5.321696418],"iteration":379,"passed_time":0.1479464719,"remaining_time":0.241386349},
{"learn":[5.318150482],"iteration":380,"passed_time":0.1481686079,"remaining_time":0.2407253761},
{"learn":[5.315358687],"iteration":381,"passed_time":0.1484472883,"remaining_time":0.2401581785},
{"learn":[5.312063186],"iteration":382,"passed_time":0.1486664658,"remaining_time":0.2394966303},
{"learn":[5.309488939],"iteration":383,"passed_time":0.1488887268,"remaining_time":0.2388423326},
{"learn":[5.307588217],"iteration":384,"passed_time":0.1491190715,"remaining_time":0.2382031922},
{"learn":[5.30543068],"iteration":385,"passed_time":0.1493833346,"remaining_time":0.2376201228},
{"learn":[5.301999181],"iteration":386,"passed_time":0.1495948867,"remaining_time":0.2369552081},
{"learn":[5.299100812],"iteration":387,"passed_time":0.1498772756,"remaining_time":0.2364043626},
{"learn":[5.297070815],"iteration":388,"passed_time":0.1501213293,"remaining_time":0.2357946844},
{"learn":[5.295231189],"iteration":389,"passed_time":0.150330048,"remaining_time":0.2351316135},
{"learn":[5.291961104],"iteration":390,"passed_time":0.1505894358,"remaining_time":0.2345497862},
{"learn":[5.289524257],"iteration":391,"passed_time":0.1508026963,"remaining_time":0.2338980596},
{"learn":[5.286355802],"iteration":392,"passed_time":0.1510248739,"remaining_time":0.2332623371},
{"learn":[5.284500396],"iteration":393,"passed_time":0.1512464266,"remaining_time":0.2326277525},
{"learn":[5.282098823],"iteration":394,"passed_time":0.1514629789,"remaining_time":0.2319876006},
{"learn":[5.27911827],"iteration":395,"passed_time":0.1516854066,"remaining_time":0.2313585494},
{"learn":[5.2769638],"iteration":396,"passed_time":0.1519115427,"remaining_time":0.2307371795},
{"learn":[5.274568862],"iteration":397,"passed_time":0.1521993903,"remaining_time":0.2302111381},
{"learn":[5.273712133],"iteration":398,"passed_time":0.1523008536,"remaining_time":0.2294055464},
{"learn":[5.271396109],"iteration":399,"passed_time":0.152538157,"remaining_time":0.2288072355},
{"learn":[5.268675951],"iteration":400,"passed_time":0.1527615847,"remaining_time":0.2281899981},
{"learn":[5.266643679],"iteration":401,"passed_time":0.1530178057,"remaining_time":0.227623502},
{"learn":[5.264157326],"iteration":402,"passed_time":0.153219399,"remaining_time":0.2269776208},
{"learn":[5.262437225],"iteration":403,"passed_time":0.1534418683,"remaining_time":0.2263647364},
{"learn":[5.259193851],"iteration":404,"passed_time":0.1536511703,"remaining_time":0.2257344354},
{"learn":[5.257394399],"iteration":405,"passed_time":0.1538025528,"remaining_time":0.2250214688},
{"learn":[5.254707957],"iteration":406,"passed_time":0.1540579821,"remaining_time":0.2244628584},
{"learn":[5.252925611],"iteration":407,"passed_time":0.1542723676,"remaining_time":0.2238461805},
{"learn":[5.250882902],"iteration":408,"passed_time":0.1544966287,"remaining_time":0.2232457398},
{"learn":[5.24927175],"iteration":409,"passed_time":0.1547308486,"remaining_time":0.2226614651},
{"learn":[5.246997374],"iteration":410,"passed_time":0.1549376088,"remaining_time":0.2220395416},
{"learn":[5.245226985],"iteration":411,"passed_time":0.1551526194,"remaining_time":0.2214314083},
{"learn":[5.243254323],"iteration":412,"passed_time":0.1553746304,"remaining_time":0.2208351284},
{"learn":[5.241206261],"iteration":413,"passed_time":0.155588766,"remaining_time":0.2202295093},
{"learn":[5.239222073],"iteration":414,"passed_time":0.15583857,"remaining_time":0.2196760565},
{"learn":[5.237277871],"iteration":415,"passed_time":0.156069248,"remaining_time":0.2190972136},
{"learn":[5.234772222],"iteration":416,"passed_time":0.1562778,"remaining_time":0.2184891065},
{"learn":[5.233338696],"iteration":417,"passed_time":0.1565326042,"remaining_time":0.2179473102},
{"learn":[5.232125823],"iteration":418,"passed_time":0.1567642823,"remaining_time":0.2173748163},
{"learn":[5.230086939],"iteration":419,"passed_time":0.1569979189,"remaining_time":0.2168066499},
{"learn":[5.228344482],"iteration":420,"passed_time":0.1572334305,"remaining_time":0.2162426515},
{"learn":[5.227632786],"iteration":421,"passed_time":0.1573216015,"remaining_time":0.2154784021},
{"learn":[5.225567755],"iteration":422,"passed_time":0.1575679887,"remaining_time":0.2149331666},
{"learn":[5.223802106],"iteration":423,"passed_time":0.1577933332,"remaining_time":0.2143607545},
{"learn":[5.222560162],"iteration":424,"passed_time":0.1579766755,"remaining_time":0.2137331493},
{"learn":[5.220563263],"iteration":425,"passed_time":0.1582180625,"remaining_time":0.21318584},
{"learn":[5.218915442],"iteration":426,"passed_time":0.1584455737,"remaining_time":0.2126213436},
{"learn":[5.216818077],"iteration":427,"passed_time":0.1586612927,"remaining_time":0.2120426622},
{"learn":[5.214791468],"iteration":428,"passed_time":0.1588788451,"remaining_time":0.2114681132},
{"learn":[5.212955206],"iteration":429,"passed_time":0.15911294,"remaining_time":0.210917153},
{"learn":[5.210892649],"iteration":430,"passed_time":0.1593435764,"remaining_time":0.2103630973},
{"learn":[5.210004949],"iteration":431,"passed_time":0.1594544152,"remaining_time":0.2096530274},
{"learn":[5.208114408],"iteration":432,"passed_time":0.1596674674,"remaining_time":0.2090795704},
{"learn":[5.206280429],"iteration":433,"passed_time":0.1599466478,"remaining_time":0.2085940154},
{"learn":[5.204676073],"iteration":434,"passed_time":0.1601857013,"remaining_time":0.2080572902},
{"learn":[5.202504746],"iteration":435,"passed_time":0.1603982951,"remaining_time":0.2074877029},
{"learn":[5.200715308],"iteration":436,"passed_time":0.1606323067,"remaining_time":0.2069473425},
{"learn":[5.197066569],"iteration":437,"passed_time":0.1608594429,"remaining_time":0.2063995591},
{"learn":[5.194195536],"iteration":438,"passed_time":0.1611193307,"remaining_time":0.2058950901},
{"learn":[5.191664245],"iteration":439,"passed_time":0.1613477587,"remaining_time":0.2053516929},
{"learn":[5.18928454],"iteration":440,"passed_time":0.1615685612,"remaining_time":0.2048000584},
{"learn":[5.187677346],"iteration":441,"passed_time":0.1617843636,"remaining_time":0.2042436083},
{"learn":[5.18611894],"iteration":442,"passed_time":0.162003041,"remaining_time":0.2036923112},
{"learn":[5.183733328],"iteration":443,"passed_time":0.1622343858,"remaining_time":0.203158375},
{"learn":[5.182083659],"iteration":444,"passed_time":0.1624795646,"remaining_time":0.2026430524},
{"learn":[5.179365231],"iteration":445,"passed_time":0.162690325,"remaining_time":0.2020861884},
{"learn":[5.177023119],"iteration":446,"passed_time":0.162934462,"remaining_time":0.2015721644},
{"learn":[5.175135606],"iteration":447,"passed_time":0.1631382221,"remaining_time":0.2010095951},
{"learn":[5.173900562],"iteration":448,"passed_time":0.1632973966,"remaining_time":0.2003939099},
{"learn":[5.172416095],"iteration":449,"passed_time":0.1635266996,"remaining_time":0.1998659662},
{"learn":[5.170983426],"iteration":450,"passed_time":0.1637473355,"remaining_time":0.1993287964},
{"learn":[5.169027439],"iteration":451,"passed_time":0.1640428501,"remaining_time":0.1988838094},
{"learn":[5.167345289],"iteration":452,"passed_time":0.1642675695,"remaining_time":0.1983539967},
{"learn":[5.164609666],"iteration":453,"passed_time":0.1644884971,"remaining_time":0.1978209679},
{"learn":[5.162789683],"iteration":454,"passed_time":0.1646908404,"remaining_time":0.1972670506},
{"learn":[5.161272846],"iteration":455,"passed_time":0.16488435,"remaining_time":0.1967041368},
{"learn":[5.160226612],"iteration":456,"passed_time":0.1650761094,"remaining_time":0.1961407602},
{"learn":[5.158800091],"iteration":457,"passed_time":0.1653131628,"remaining_time":0.1956326075},
{"learn":[5.157387131],"iteration":458,"passed_time":0.1655091308,"remaining_time":0.1950772108},
{"learn":[5.155805189],"iteration":459,"passed_time":0.1657205579,"remaining_time":0.1945415245},
{"learn":[5.154227742],"iteration":460,"passed_time":0.1659391937,"remaining_time":0.1940156734},
{"learn":[5.152545462],"iteration":461,"passed_time":0.1661916228,"remaining_time":0.1935305045},
{"learn":[5.150804038],"iteration":462,"passed_time":0.1664312597,"remaining_time":0.1930315042},
{"learn":[5.14886445],"iteration":463,"passed_time":0.1666683547,"remaining_time":0.1925306856},
{"learn":[5.14746514],"iteration":464,"passed_time":0.1669097416,"remaining_time":0.1920359393},
{"learn":[5.145692347],"iteration":465,"passed_time":0.1671351278,"remaining_time":0.1915239447},
{"learn":[5.144964968],"iteration":466,"passed_time":0.1672487584,"remaining_time":0.1908856279},
{"learn":[5.14366654],"iteration":467,"passed_time":0.1674759779,"remaining_time":0.1903786758},
{"learn":[5.141808346],"iteration":468,"passed_time":0.1676915719,"remaining_time":0.1898597541},
{"learn":[5.13967506],"iteration":469,"passed_time":0.1679229583,"remaining_time":0.1893599317},
{"learn":[5.137787746],"iteration":470,"passed_time":0.1681485945,"remaining_time":0.1888547908},
{"learn":[5.136286016],"iteration":471,"passed_time":0.1683815643,"remaining_time":0.1883590381},
{"learn":[5.134700571],"iteration":472,"passed_time":0.1685975333,"remaining_time":0.1878454547},
{"learn":[5.133426045],"iteration":473,"passed_time":0.1688186692,"remaining_time":0.1873388608},
{"learn":[5.131459972],"iteration":474,"passed_time":0.1690641814,"remaining_time":0.186860411},
{"learn":[5.129830954],"iteration":475,"passed_time":0.1692798587,"remaining_time":0.1863500965},
{"learn":[5.127264562],"iteration":476,"passed_time":0.1694875773,"remaining_time":0.1858322912},
{"learn":[5.125000568],"iteration":477,"passed_time":0.1697169636,"remaining_time":0.1853394456},
{"learn":[5.123504441],"iteration":478,"passed_time":0.1699427247,"remaining_time":0.184843757},
{"learn":[5.121260712],"iteration":479,"passed_time":0.170164569,"remaining_time":0.1843449498},
{"learn":[5.119555181],"iteration":480,"passed_time":0.1703885801,"remaining_time":0.1838496322},
{"learn":[5.118934014],"iteration":481,"passed_time":0.1705011273,"remaining_time":0.1832356513},
{"learn":[5.117427961],"iteration":482,"passed_time":0.1707108877,"remaining_time":0.1827278032},
{"learn":[5.1159761],"iteration":483,"passed_time":0.1709244815,"remaining_time":0.1822252737},
{"learn":[5.113904653],"iteration":484,"passed_time":0.1711421173,"remaining_time":0.1817282276},
{"learn":[5.11191646],"iteration":485,"passed_time":0.1713502109,"remaining_time":0.1812222395},
{"learn":[5.10969012],"iteration":486,"passed_time":0.1716171824,"remaining_time":0.1807794961},
{"learn":[5.108061795],"iteration":487,"passed_time":0.171857736,"remaining_time":0.1803097558},
{"learn":[5.106641113],"iteration":488,"passed_time":0.1720891641,"remaining_time":0.1798314168},
{"learn":[5.105193342],"iteration":489,"passed_time":0.1723186754,"remaining_time":0.1793520907},
{"learn":[5.104241691],"iteration":490,"passed_time":0.1725218521,"remaining_time":0.1788464821},
{"learn":[5.102884832],"iteration":491,"passed_time":0.1727303207,"remaining_time":0.1783475669},
{"learn":[5.10115623],"iteration":492,"passed_time":0.172946248,"remaining_time":0.1778575005},
{"learn":[5.100323599],"iteration":493,"passed_time":0.1731894684,"remaining_time":0.1773965},
{"learn":[5.099553902],"iteration":494,"passed_time":0.1734041873,"remaining_time":0.1769073022},
{"learn":[5.098165573],"iteration":495,"passed_time":0.1736314902,"remaining_time":0.1764319981},
{"learn":[5.096032368],"iteration":496,"passed_time":0.1738525845,"remaining_time":0.1759514084},
{"learn":[5.094801517],"iteration":497,"passed_time":0.1740861377,"remaining_time":0.1754844199},
{"learn":[5.09397602],"iteration":498,"passed_time":0.1743168157,"remaining_time":0.1750154803},
{"learn":[5.09283838],"iteration":499,"passed_time":0.174552744,"remaining_time":0.174552744},
{"learn":[5.091830746],"iteration":500,"passed_time":0.1747650462,"remaining_time":0.1740673813},
{"learn":[5.090273051],"iteration":501,"passed_time":0.174997641,"remaining_time":0.1736032375},
{"learn":[5.088733322],"iteration":502,"passed_time":0.1752184436,"remaining_time":0.1731283627},
{"learn":[5.087093288],"iteration":503,"passed_time":0.1754421213,"remaining_time":0.1726573257},
{"learn":[5.084832735],"iteration":504,"passed_time":0.1756900502,"remaining_time":0.1722110393},
{"learn":[5.083404947],"iteration":505,"passed_time":0.1759055192,"remaining_time":0.1717338468},
{"learn":[5.08251745],"iteration":506,"passed_time":0.1761434059,"remaining_time":0.1712794854},
{"learn":[5.081328012],"iteration":507,"passed_time":0.1763700838,"remaining_time":0.1708151205},
{"learn":[5.079123028],"iteration":508,"passed_time":0.1765890946,"remaining_time":0.1703442936},
{"learn":[5.077149797],"iteration":509,"passed_time":0.1767924796,"remaining_time":0.1698594412},
{"learn":[5.07543215],"iteration":510,"passed_time":0.1769940729,"remaining_time":0.1693739758},
{"learn":[5.073794666],"iteration":511,"passed_time":0.1772090835,"remaining_time":0.1689024077},
{"learn":[5.072016419],"iteration":512,"passed_time":0.177535683,"remaining_time":0.1685377731},
{"learn":[5.070987715],"iteration":513,"passed_time":0.1777409431,"remaining_time":0.1680585571},
{"learn":[5.069880608],"iteration":514,"passed_time":0.1779538703,"remaining_time":0.1675876254},
{"learn":[5.068075532],"iteration":515,"passed_time":0.1781850067,"remaining_time":0.1671347737},
{"learn":[5.066052054],"iteration":516,"passed_time":0.1783890585,"remaining_time":0.1666574763},
{"learn":[5.064588197],"iteration":517,"passed_time":0.1785941936,"remaining_time":0.1661822419},
{"learn":[5.062981414],"iteration":518,"passed_time":0.178817413,"remaining_time":0.1657248085},
{"learn":[5.061964173],"iteration":519,"passed_time":0.1790395073,"remaining_time":0.1652672375},
{"learn":[5.06086023],"iteration":520,"passed_time":0.1792442257,"remaining_time":0.1647945952},
{"learn":[5.059900302],"iteration":521,"passed_time":0.1794788623,"remaining_time":0.1643503758},
{"learn":[5.058479391],"iteration":522,"passed_time":0.1797107487,"remaining_time":0.1639044496},
{"learn":[5.056262825],"iteration":523,"passed_time":0.1799167589,"remaining_time":0.1634358344},
{"learn":[5.056020073],"iteration":524,"passed_time":0.1799980546,"remaining_time":0.1628553827},
{"learn":[5.055259164],"iteration":525,"passed_time":0.1802339829,"remaining_time":0.1624161747},
{"learn":[5.053337859],"iteration":526,"passed_time":0.1804534937,"remaining_time":0.1619630029},
{"learn":[5.051935305],"iteration":527,"passed_time":0.1806822134,"remaining_time":0.1615189483},
{"learn":[5.050391217],"iteration":528,"passed_time":0.1809130164,"remaining_time":0.1610775628},
{"learn":[5.049467802],"iteration":529,"passed_time":0.1811366941,"remaining_time":0.1606306533},
{"learn":[5.047782094],"iteration":530,"passed_time":0.18135583,"remaining_time":0.160180573},
{"learn":[5.045645064],"iteration":531,"passed_time":0.1815758825,"remaining_time":0.1597321673},
{"learn":[5.045349109],"iteration":532,"passed_time":0.181654678,"remaining_time":0.159160853},
{"learn":[5.044466417],"iteration":533,"passed_time":0.1818938149,"remaining_time":0.1587313066},
{"learn":[5.043318328],"iteration":534,"passed_time":0.1820958665,"remaining_time":0.1582702391},
{"learn":[5.041910158],"iteration":535,"passed_time":0.1823190442,"remaining_time":0.1578284263},
{"learn":[5.040582262],"iteration":536,"passed_time":0.1825525974,"remaining_time":0.1573963735},
{"learn":[5.039275272],"iteration":537,"passed_time":0.1827657329,"remaining_time":0.1569475253},
{"learn":[5.037667306],"iteration":538,"passed_time":0.1829768267,"remaining_time":0.1564978054},
{"learn":[5.035237894],"iteration":539,"passed_time":0.1832131717,"remaining_time":0.1560704796},
{"learn":[5.034307838],"iteration":540,"passed_time":0.1834444331,"remaining_time":0.1556395467},
{"learn":[5.032985676],"iteration":541,"passed_time":0.1836670691,"remaining_time":0.1552020621},
{"learn":[5.031796366],"iteration":542,"passed_time":0.1838847882,"remaining_time":0.1547612306},
{"learn":[5.031119994],"iteration":543,"passed_time":0.1840822563,"remaining_time":0.1543042442},
{"learn":[5.03004769],"iteration":544,"passed_time":0.1842910582,"remaining_time":0.1538576725},
{"learn":[5.0285172],"iteration":545,"passed_time":0.1845257365,"remaining_time":0.1534334878},
{"learn":[5.02667778],"iteration":546,"passed_time":0.1847372886,"remaining_time":0.1529908441},
{"learn":[5.025493912],"iteration":547,"passed_time":0.1849419654,"remaining_time":0.1525433729},
{"learn":[5.024276785],"iteration":548,"passed_time":0.1851719351,"remaining_time":0.1521175641},
{"learn":[5.023310875],"iteration":549,"passed_time":0.1853916126,"remaining_time":0.1516840466},
{"learn":[5.02213108],"iteration":550,"passed_time":0.1856627093,"remaining_time":0.1512932059},
{"learn":[5.020839738],"iteration":551,"passed_time":0.1858911789,"remaining_time":0.1508682032},
{"learn":[5.019677022],"iteration":552,"passed_time":0.1861099814,"remaining_time":0.1504360971},
{"learn":[5.018260216],"iteration":553,"passed_time":0.18635116,"remaining_time":0.150022775},
{"learn":[5.016416415],"iteration":554,"passed_time":0.1865856299,"remaining_time":0.1496046942},
{"learn":[5.01519109],"iteration":555,"passed_time":0.1867853064,"remaining_time":0.1491594893},
{"learn":[5.014148616],"iteration":556,"passed_time":0.1869764408,"remaining_time":0.1487083721},
{"learn":[5.012300991],"iteration":557,"passed_time":0.1871982851,"remaining_time":0.1482825126},
{"learn":[5.010799757],"iteration":558,"passed_time":0.1874200877,"remaining_time":0.1478573501},
{"learn":[5.00897997],"iteration":559,"passed_time":0.1876688917,"remaining_time":0.1474541292},
{"learn":[5.007536435],"iteration":560,"passed_time":0.1878668598,"remaining_time":0.1470116782},
{"learn":[5.006502343],"iteration":561,"passed_time":0.1880800787,"remaining_time":0.146581983},
{"learn":[5.005355112],"iteration":562,"passed_time":0.1882885473,"remaining_time":0.1461493697},
{"learn":[5.003683668],"iteration":563,"passed_time":0.1884929324,"remaining_time":0.1457143945},
{"learn":[5.002212512],"iteration":564,"passed_time":0.1886936506,"remaining_time":0.1452774124},
{"learn":[5.000479759],"iteration":565,"passed_time":0.1889199535,"remaining_time":0.144860883},
{"learn":[4.998958408],"iteration":566,"passed_time":0.1891343807,"remaining_time":0.1444359556},
{"learn":[4.998055938],"iteration":567,"passed_time":0.1893335572,"remaining_time":0.1440001703},
{"learn":[4.996235269],"iteration":568,"passed_time":0.1896037372,"remaining_time":0.1436189995},
{"learn":[4.995373817],"iteration":569,"passed_time":0.1898347486,"remaining_time":0.14320867},
{"learn":[4.994417882],"iteration":570,"passed_time":0.1900525511,"remaining_time":0.1427890445},
{"learn":[4.99348533],"iteration":571,"passed_time":0.1903103971,"remaining_time":0.1424000874},
{"learn":[4.992670264],"iteration":572,"passed_time":0.1905220742,"remaining_time":0.1419771827},
{"learn":[4.992152306],"iteration":573,"passed_time":0.1906347465,"remaining_time":0.1414815366},
{"learn":[4.991103853],"iteration":574,"passed_time":0.190848257,"remaining_time":0.1410617552},
{"learn":[4.990200566],"iteration":575,"passed_time":0.1910431833,"remaining_time":0.1406290099},
{"learn":[4.988582926],"iteration":576,"passed_time":0.1912617774,"remaining_time":0.14021444},
{"learn":[4.986954585],"iteration":577,"passed_time":0.1915029977,"remaining_time":0.1398170675},
{"learn":[4.985682921],"iteration":578,"passed_time":0.1917244253,"remaining_time":0.1394058429},
{"learn":[4.983656516],"iteration":579,"passed_time":0.1919430611,"remaining_time":0.1389932511},
{"learn":[4.982697884],"iteration":580,"passed_time":0.1922025739,"remaining_time":0.1386108063},
{"learn":[4.981509667],"iteration":581,"passed_time":0.1924341687,"remaining_time":0.1382087328},
{"learn":[4.980571857],"iteration":582,"passed_time":0.1926634716,"remaining_time":0.1378056049},
{"learn":[4.979586021],"iteration":583,"passed_time":0.1928783572,"remaining_time":0.1373928024},
{"learn":[4.978826449],"iteration":584,"passed_time":0.1930957847,"remaining_time":0.1369824797},
{"learn":[4.977594762],"iteration":585,"passed_time":0.1933100452,"remaining_time":0.136570578},
{"learn":[4.976299069],"iteration":586,"passed_time":0.1935200973,"remaining_time":0.1361563887},
{"learn":[4.975687717],"iteration":587,"passed_time":0.1937143152,"remaining_time":0.1357317991},
{"learn":[4.975099395],"iteration":588,"passed_time":0.1939738697,"remaining_time":0.1353535831},
{"learn":[4.973395154],"iteration":589,"passed_time":0.1942320491,"remaining_time":0.1349748138},
{"learn":[4.971336448],"iteration":590,"passed_time":0.1944669357,"remaining_time":0.1345803328},
{"learn":[4.970086483],"iteration":591,"passed_time":0.194682863,"remaining_time":0.1341733245},
{"learn":[4.968842926],"iteration":592,"passed_time":0.1949420842,"remaining_time":0.133796675},
{"learn":[4.967145998],"iteration":593,"passed_time":0.1951655952,"remaining_time":0.1333960129},
{"learn":[4.966394084],"iteration":594,"passed_time":0.1954163992,"remaining_time":0.1330145239},
{"learn":[4.965489491],"iteration":595,"passed_time":0.1956409937,"remaining_time":0.1326157071},
{"learn":[4.964535983],"iteration":596,"passed_time":0.1958717551,"remaining_time":0.132221637},
{"learn":[4.963901632],"iteration":597,"passed_time":0.1961148921,"remaining_time":0.1318364325},
{"learn":[4.962606325],"iteration":598,"passed_time":0.1963510287,"remaining_time":0.1314470159},
{"learn":[4.961288394],"iteration":599,"passed_time":0.1965980409,"remaining_time":0.1310653606},
{"learn":[4.959987331],"iteration":600,"passed_time":0.1968313858,"remaining_time":0.1306750797},
{"learn":[4.958499739],"iteration":601,"passed_time":0.197057772,"remaining_time":0.1302807197},
{"learn":[4.956953907],"iteration":602,"passed_time":0.197267074,"remaining_time":0.1298756689},
{"learn":[4.955635205],"iteration":603,"passed_time":0.1974862514,"remaining_time":0.129477741},
{"learn":[4.95375998],"iteration":604,"passed_time":0.1976962201,"remaining_time":0.1290743917},
{"learn":[4.952364937],"iteration":605,"passed_time":0.1979169394,"remaining_time":0.1286786702},
{"learn":[4.950625725],"iteration":606,"passed_time":0.1981495759,"remaining_time":0.128291241},
{"learn":[4.9500437],"iteration":607,"passed_time":0.1983849625,"remaining_time":0.1279060942},
{"learn":[4.949493617],"iteration":608,"passed_time":0.1986069734,"remaining_time":0.1275128516},
{"learn":[4.948778583],"iteration":609,"passed_time":0.1988126919,"remaining_time":0.1271097539},
{"learn":[4.947083724],"iteration":610,"passed_time":0.1990350363,"remaining_time":0.1267178872},
{"learn":[4.946460045],"iteration":611,"passed_time":0.1992236706,"remaining_time":0.1263052029},
{"learn":[4.945468049],"iteration":612,"passed_time":0.1994515985,"remaining_time":0.1259180565},
{"learn":[4.94462259],"iteration":613,"passed_time":0.1997039026,"remaining_time":0.1255467531},
{"learn":[4.943499463],"iteration":614,"passed_time":0.1999257886,"remaining_time":0.1251567945},
{"learn":[4.941619332],"iteration":615,"passed_time":0.2001602168,"remaining_time":0.1247752001},
{"learn":[4.940647371],"iteration":616,"passed_time":0.2003777692,"remaining_time":0.1243836072},
{"learn":[4.939847945],"iteration":617,"passed_time":0.2006160727,"remaining_time":0.1240054041},
{"learn":[4.938775942],"iteration":618,"passed_time":0.2008081238,"remaining_time":0.1235991844},
{"learn":[4.937313026],"iteration":619,"passed_time":0.2010085504,"remaining_time":0.1231987889},
{"learn":[4.936353082],"iteration":620,"passed_time":0.2012417702,"remaining_time":0.1228190514},
{"learn":[4.934987975],"iteration":621,"passed_time":0.2014768652,"remaining_time":0.1224409245},
{"learn":[4.933272778],"iteration":622,"passed_time":0.2016818753,"remaining_time":0.1220450513},
{"learn":[4.932230126],"iteration":623,"passed_time":0.201892969,"remaining_time":0.1216534557},
{"learn":[4.931104328],"iteration":624,"passed_time":0.202149065,"remaining_time":0.121289439},
{"learn":[4.930617792],"iteration":625,"passed_time":0.202352075,"remaining_time":0.1208940512},
{"learn":[4.929134968],"iteration":626,"passed_time":0.2025598353,"remaining_time":0.120502103},
{"learn":[4.928032687],"iteration":627,"passed_time":0.2027865548,"remaining_time":0.120121972},
{"learn":[4.927226639],"iteration":628,"passed_time":0.2030418174,"remaining_time":0.1197591642},
{"learn":[4.925973679],"iteration":629,"passed_time":0.2032677453,"remaining_time":0.1193794694},
{"learn":[4.924021974],"iteration":630,"passed_time":0.2034619215,"remaining_time":0.1189816942},
{"learn":[4.923148186],"iteration":631,"passed_time":0.2036731819,"remaining_time":0.118594511},
{"learn":[4.921877493],"iteration":632,"passed_time":0.2038874009,"remaining_time":0.1182095989},
{"learn":[4.920658284],"iteration":633,"passed_time":0.2041042449,"remaining_time":0.1178267407},
{"learn":[4.919468646],"iteration":634,"passed_time":0.2043116718,"remaining_time":0.1174389925},
{"learn":[4.918262759],"iteration":635,"passed_time":0.2045934774,"remaining_time":0.1170943801},
{"learn":[4.917233642],"iteration":636,"passed_time":0.2048041128,"remaining_time":0.1167094081},
{"learn":[4.916315385],"iteration":637,"passed_time":0.2050168316,"remaining_time":0.1163261647},
{"learn":[4.915161715],"iteration":638,"passed_time":0.2052209667,"remaining_time":0.1159386056},
{"learn":[4.913760533],"iteration":639,"passed_time":0.2054530198,"remaining_time":0.1155673237},
{"learn":[4.912868894],"iteration":640,"passed_time":0.2056769892,"remaining_time":0.1151919487},
{"learn":[4.911488132],"iteration":641,"passed_time":0.2059469192,"remaining_time":0.1148426746},
{"learn":[4.911161533],"iteration":642,"passed_time":0.20613247,"remaining_time":0.1144467991},
{"learn":[4.910412917],"iteration":643,"passed_time":0.206347939,"remaining_time":0.1140681154},
{"learn":[4.909619933],"iteration":644,"passed_time":0.2065986597,"remaining_time":0.1137093399},
{"learn":[4.908546042],"iteration":645,"passed_time":0.2068283794,"remaining_time":0.1133393906},
{"learn":[4.906984654],"iteration":646,"passed_time":0.2070408899,"remaining_time":0.1129604855},
{"learn":[4.905261588],"iteration":647,"passed_time":0.207231441,"remaining_time":0.1125701655},
{"learn":[4.903982378],"iteration":648,"passed_time":0.2074654109,"remaining_time":0.1122039433},
{"learn":[4.902691843],"iteration":649,"passed_time":0.2076812132,"remaining_time":0.1118283456},
{"learn":[4.902120511],"iteration":650,"passed_time":0.2079136413,"remaining_time":0.1114621518},
{"learn":[4.901626464],"iteration":651,"passed_time":0.2081440277,"remaining_time":0.1110952786},
{"learn":[4.900998913],"iteration":652,"passed_time":0.2083443709,"remaining_time":0.1107128587},
{"learn":[4.900252359],"iteration":653,"passed_time":0.2085640068,"remaining_time":0.1103412024},
{"learn":[4.899233441],"iteration":654,"passed_time":0.2087832259,"remaining_time":0.1099697908},
{"learn":[4.897774626],"iteration":655,"passed_time":0.2090006117,"remaining_time":0.1095978817},
{"learn":[4.897135563],"iteration":656,"passed_time":0.209223581,"remaining_time":0.1092293581},
{"learn":[4.896045184],"iteration":657,"passed_time":0.2094420918,"remaining_time":0.1088589596},
{"learn":[4.89419148],"iteration":658,"passed_time":0.2096523522,"remaining_time":0.1084847528},
{"learn":[4.892721728],"iteration":659,"passed_time":0.2098514037,"remaining_time":0.1081052686},
{"learn":[4.89123157],"iteration":660,"passed_time":0.2100717896,"remaining_time":0.1077372718},
{"learn":[4.891068007],"iteration":661,"passed_time":0.21014871,"remaining_time":0.1072964713},
{"learn":[4.890179923],"iteration":662,"passed_time":0.2103722211,"remaining_time":0.1069312798},
{"learn":[4.889240981],"iteration":663,"passed_time":0.2105535633,"remaining_time":0.1065451766},
{"learn":[4.887812947],"iteration":664,"passed_time":0.2107719075,"remaining_time":0.1061783293},
{"learn":[4.887075718],"iteration":665,"passed_time":0.2110250866,"remaining_time":0.1058293978},
{"learn":[4.885890674],"iteration":666,"passed_time":0.2112625567,"remaining_time":0.1054729106},
{"learn":[4.884441029],"iteration":667,"passed_time":0.2114721087,"remaining_time":0.1051029043},
{"learn":[4.883812468],"iteration":668,"passed_time":0.2117176208,"remaining_time":0.1047511696},
{"learn":[4.883117154],"iteration":669,"passed_time":0.211951549,"remaining_time":0.1043940465},
{"learn":[4.88191305],"iteration":670,"passed_time":0.212193686,"remaining_time":0.1040413155},
{"learn":[4.88042259],"iteration":671,"passed_time":0.2124164053,"remaining_time":0.1036794359},
{"learn":[4.879168451],"iteration":672,"passed_time":0.212639833,"remaining_time":0.1033183141},
{"learn":[4.878123701],"iteration":673,"passed_time":0.2128795115,"remaining_time":0.1029654611},
{"learn":[4.877471188],"iteration":674,"passed_time":0.2131155232,"remaining_time":0.1026111778},
{"learn":[4.875907516],"iteration":675,"passed_time":0.2133561184,"remaining_time":0.1022594414},
{"learn":[4.875356512],"iteration":676,"passed_time":0.213598047,"remaining_time":0.1019086694},
{"learn":[4.874729961],"iteration":677,"passed_time":0.2138065156,"remaining_time":0.1015423275},
{"learn":[4.873761351],"iteration":678,"passed_time":0.2140229847,"remaining_time":0.1011802328},
{"learn":[4.87269833],"iteration":679,"passed_time":0.2142639132,"remaining_time":0.1008300768},
{"learn":[4.871311487],"iteration":680,"passed_time":0.2144797155,"remaining_time":0.1004684717},
{"learn":[4.870340567],"iteration":681,"passed_time":0.2146915593,"remaining_time":0.1001054485},
{"learn":[4.869039951],"iteration":682,"passed_time":0.2149126536,"remaining_time":0.09974716133},
{"learn":[4.868415211],"iteration":683,"passed_time":0.2151055798,"remaining_time":0.099376262},
{"learn":[4.867932631],"iteration":684,"passed_time":0.21531234,"remaining_time":0.09901224394},
{"learn":[4.866905276],"iteration":685,"passed_time":0.2155381011,"remaining_time":0.09865738157},
{"learn":[4.866294876],"iteration":686,"passed_time":0.2157719877,"remaining_time":0.09830659701},
{"learn":[4.865351904],"iteration":687,"passed_time":0.2160102495,"remaining_time":0.09795813638},
{"learn":[4.863908093],"iteration":688,"passed_time":0.216222885,"remaining_time":0.09759842848},
{"learn":[4.862541858],"iteration":689,"passed_time":0.2164477294,"remaining_time":0.09724463204},
{"learn":[4.861374837],"iteration":690,"passed_time":0.2167036587,"remaining_time":0.09690510931},
{"learn":[4.860446086],"iteration":691,"passed_time":0.2169372119,"remaining_time":0.09655586888},
{"learn":[4.859402003],"iteration":692,"passed_time":0.2171518475,"remaining_time":0.09619858179},
{"learn":[4.858418355],"iteration":693,"passed_time":0.2173581077,"remaining_time":0.09583801289},
{"learn":[4.857374343],"iteration":694,"passed_time":0.2175962861,"remaining_time":0.09549189534},
{"learn":[4.855547373],"iteration":695,"passed_time":0.2178749665,"remaining_time":0.09516377848},
{"learn":[4.854075902],"iteration":696,"passed_time":0.2180984776,"remaining_time":0.09481182023},
{"learn":[4.852812499],"iteration":697,"passed_time":0.21831578,"remaining_time":0.09445754377},
{"learn":[4.851479262],"iteration":698,"passed_time":0.2185418745,"remaining_time":0.09410744522},
{"learn":[4.850667763],"iteration":699,"passed_time":0.2187712608,"remaining_time":0.09375911177},
{"learn":[4.849501355],"iteration":700,"passed_time":0.2189897299,"remaining_time":0.09340646112},
{"learn":[4.848448585],"iteration":701,"passed_time":0.2192075323,"remaining_time":0.09305390973},
{"learn":[4.848101422],"iteration":702,"passed_time":0.2194235847,"remaining_time":0.09270100234},
{"learn":[4.84642222],"iteration":703,"passed_time":0.219741517,"remaining_time":0.09239131966},
{"learn":[4.844956555],"iteration":704,"passed_time":0.2199614862,"remaining_time":0.09204062189},
{"learn":[4.844107274],"iteration":705,"passed_time":0.2201794553,"remaining_time":0.09168946156},
{"learn":[4.84324001],"iteration":706,"passed_time":0.2203976744,"remaining_time":0.09133878162},
{"learn":[4.842099304],"iteration":707,"passed_time":0.2206905222,"remaining_time":0.09101925493},
{"learn":[4.840577591],"iteration":708,"passed_time":0.2208981575,"remaining_time":0.09066482909},
{"learn":[4.838751083],"iteration":709,"passed_time":0.2211387944,"remaining_time":0.09032429629},
{"learn":[4.83759516],"iteration":710,"passed_time":0.221394932,"remaining_time":0.08999034508},
{"learn":[4.836986496],"iteration":711,"passed_time":0.2216049424,"remaining_time":0.08963795422},
{"learn":[4.835200003],"iteration":712,"passed_time":0.2218286201,"remaining_time":0.08929146419},
{"learn":[4.834518948],"iteration":713,"passed_time":0.2220537979,"remaining_time":0.08894591903},
{"learn":[4.833569896],"iteration":714,"passed_time":0.2222690168,"remaining_time":0.08859674097},
{"learn":[4.83258966],"iteration":715,"passed_time":0.2224867359,"remaining_time":0.08824892877},
{"learn":[4.831511256],"iteration":716,"passed_time":0.2227005798,"remaining_time":0.08789994991},
{"learn":[4.830501884],"iteration":717,"passed_time":0.2229095901,"remaining_time":0.08754944905},
{"learn":[4.829652914],"iteration":718,"passed_time":0.2231391431,"remaining_time":0.08720737026},
{"learn":[4.828311735],"iteration":719,"passed_time":0.2233536537,"remaining_time":0.08685975422},
{"learn":[4.827288726],"iteration":720,"passed_time":0.2235639141,"remaining_time":0.08651086274},
{"learn":[4.826141909],"iteration":721,"passed_time":0.2237850084,"remaining_time":0.08616652676},
{"learn":[4.82503713],"iteration":722,"passed_time":0.2239993523,"remaining_time":0.08581994548},
{"learn":[4.823521065],"iteration":723,"passed_time":0.2242064458,"remaining_time":0.08547096554},
{"learn":[4.82152105],"iteration":724,"passed_time":0.2244134561,"remaining_time":0.0851223454},
{"learn":[4.82063078],"iteration":725,"passed_time":0.2246331336,"remaining_time":0.08477889614},
{"learn":[4.819886644],"iteration":726,"passed_time":0.2248362269,"remaining_time":0.08442955977},
{"learn":[4.818345569],"iteration":727,"passed_time":0.2250548627,"remaining_time":0.08408643223},
{"learn":[4.816970512],"iteration":728,"passed_time":0.225276832,"remaining_time":0.08374488543},
{"learn":[4.815859459],"iteration":729,"passed_time":0.2255076767,"remaining_time":0.08340694893},
{"learn":[4.814550719],"iteration":730,"passed_time":0.2257249375,"remaining_time":0.08306430668},
{"learn":[4.813280125],"iteration":731,"passed_time":0.2260020762,"remaining_time":0.08274392952},
{"learn":[4.812155824],"iteration":732,"passed_time":0.2262029194,"remaining_time":0.08239587924},
{"learn":[4.811570998],"iteration":733,"passed_time":0.2264029293,"remaining_time":0.08204792805},
{"learn":[4.81055688],"iteration":734,"passed_time":0.2266278571,"remaining_time":0.08170936343},
{"learn":[4.809202216],"iteration":735,"passed_time":0.2268386175,"remaining_time":0.08136602583},
{"learn":[4.808193038],"iteration":736,"passed_time":0.2270983803,"remaining_time":0.08104053462},
{"learn":[4.807568969],"iteration":737,"passed_time":0.2273012653,"remaining_time":0.08069502915},
{"learn":[4.8071664],"iteration":738,"passed_time":0.2275433189,"remaining_time":0.08036374322},
{"learn":[4.806583063],"iteration":739,"passed_time":0.2277832474,"remaining_time":0.0800319518},
{"learn":[4.8058723],"iteration":740,"passed_time":0.2280081752,"remaining_time":0.07969516516},
{"learn":[4.804987119],"iteration":741,"passed_time":0.2282523123,"remaining_time":0.07936535925},
{"learn":[4.804485652],"iteration":742,"passed_time":0.2284529472,"remaining_time":0.07902073678},
{"learn":[4.803253472],"iteration":743,"passed_time":0.2286762915,"remaining_time":0.07868431537},
{"learn":[4.802445549],"iteration":744,"passed_time":0.2289551386,"remaining_time":0.07836719511},
{"learn":[4.801981126],"iteration":745,"passed_time":0.2291853583,"remaining_time":0.07803362067},
{"learn":[4.800950064],"iteration":746,"passed_time":0.2294024524,"remaining_time":0.07769587745},
{"learn":[4.799975505],"iteration":747,"passed_time":0.2295977537,"remaining_time":0.07735111489},
{"learn":[4.799363103],"iteration":748,"passed_time":0.2298040972,"remaining_time":0.07701045181},
{"learn":[4.798216843],"iteration":749,"passed_time":0.2300302334,"remaining_time":0.07667674447},
{"learn":[4.797248009],"iteration":750,"passed_time":0.2302228262,"remaining_time":0.07633220204},
{"learn":[4.796212995],"iteration":751,"passed_time":0.2304658382,"remaining_time":0.07600469133},
{"learn":[4.794794436],"iteration":752,"passed_time":0.2306749319,"remaining_time":0.07566627912},
{"learn":[4.79296241],"iteration":753,"passed_time":0.2309036099,"remaining_time":0.0753345995},
{"learn":[4.792538113],"iteration":754,"passed_time":0.2311058698,"remaining_time":0.07499462001},
{"learn":[4.791310478],"iteration":755,"passed_time":0.2313457984,"remaining_time":0.07466716243},
{"learn":[4.789394289],"iteration":756,"passed_time":0.2316349793,"remaining_time":0.07435574633},
{"learn":[4.787989827],"iteration":757,"passed_time":0.2318620738,"remaining_time":0.07402456711},
{"learn":[4.78752571],"iteration":758,"passed_time":0.2320777512,"remaining_time":0.07369003693},
{"learn":[4.786206978],"iteration":759,"passed_time":0.2322980537,"remaining_time":0.07335728012},
{"learn":[4.785690652],"iteration":760,"passed_time":0.232533607,"remaining_time":0.07302960851},
{"learn":[4.784979413],"iteration":761,"passed_time":0.2327524928,"remaining_time":0.07269697282},
{"learn":[4.78417189],"iteration":762,"passed_time":0.2329689618,"remaining_time":0.07236388461},
{"learn":[4.783818392],"iteration":763,"passed_time":0.2331826807,"remaining_time":0.07203025216},
{"learn":[4.783122099],"iteration":764,"passed_time":0.2334269428,"remaining_time":0.07170631576},
{"learn":[4.782246182],"iteration":765,"passed_time":0.2336641212,"remaining_time":0.07138042344},
{"learn":[4.780871003],"iteration":766,"passed_time":0.2338640477,"remaining_time":0.07104344604},
{"learn":[4.779877073],"iteration":767,"passed_time":0.2340975176,"remaining_time":0.07071695843},
{"learn":[4.778875031],"iteration":768,"passed_time":0.2343057362,"remaining_time":0.07038312751},
{"learn":[4.777736351],"iteration":769,"passed_time":0.2345297472,"remaining_time":0.07005434008},
{"learn":[4.777177987],"iteration":770,"passed_time":0.2347670923,"remaining_time":0.06972978487},
{"learn":[4.776650654],"iteration":771,"passed_time":0.2349718941,"remaining_time":0.06939584436},
{"learn":[4.775968014],"iteration":772,"passed_time":0.2351865297,"remaining_time":0.06906512579},
{"learn":[4.775326518],"iteration":773,"passed_time":0.2354056655,"remaining_time":0.06873602119},
{"learn":[4.774037179],"iteration":774,"passed_time":0.2356383436,"remaining_time":0.06841113203},
{"learn":[4.772011252],"iteration":775,"passed_time":0.2358666883,"remaining_time":0.0680852296},
{"learn":[4.770658507],"iteration":776,"passed_time":0.2360990331,"remaining_time":0.06776072635},
{"learn":[4.769791797],"iteration":777,"passed_time":0.2363294611,"remaining_time":0.06743591307},
{"learn":[4.768841914],"iteration":778,"passed_time":0.2365408465,"remaining_time":0.06710593978},
{"learn":[4.767937787],"iteration":779,"passed_time":0.2367571489,"remaining_time":0.06677765738},
{"learn":[4.767047955],"iteration":780,"passed_time":0.2369771181,"remaining_time":0.06645068996},
{"learn":[4.766337199],"iteration":781,"passed_time":0.2372137131,"remaining_time":0.06612863102},
{"learn":[4.765329094],"iteration":782,"passed_time":0.2374505998,"remaining_time":0.06580687121},
{"learn":[4.764222232],"iteration":783,"passed_time":0.2376538182,"remaining_time":0.06547605194},
{"learn":[4.762993541],"iteration":784,"passed_time":0.2378759125,"remaining_time":0.06515072762},
{"learn":[4.761973223],"iteration":785,"passed_time":0.2381197162,"remaining_time":0.06483157667},
{"learn":[4.761000381],"iteration":786,"passed_time":0.2383352685,"remaining_time":0.06450497101},
{"learn":[4.759956782],"iteration":787,"passed_time":0.238588906,"remaining_time":0.06418889349},
{"learn":[4.759422123],"iteration":788,"passed_time":0.2388279595,"remaining_time":0.06386907408},
{"learn":[4.758519158],"iteration":789,"passed_time":0.2390530956,"remaining_time":0.06354575959},
{"learn":[4.75734286],"iteration":790,"passed_time":0.2393316927,"remaining_time":0.06323681893},
{"learn":[4.756338343],"iteration":791,"passed_time":0.2395852885,"remaining_time":0.06292138891},
{"learn":[4.755327755],"iteration":792,"passed_time":0.2397983824,"remaining_time":0.06259554244},
{"learn":[4.754869069],"iteration":793,"passed_time":0.2400395193,"remaining_time":0.06227725564},
{"learn":[4.754123222],"iteration":794,"passed_time":0.24025553,"remaining_time":0.06195268383},
{"learn":[4.752198349],"iteration":795,"passed_time":0.2404793744,"remaining_time":0.06163039242},
{"learn":[4.751009538],"iteration":796,"passed_time":0.2406874263,"remaining_time":0.06130432564},
{"learn":[4.750499638],"iteration":797,"passed_time":0.240911604,"remaining_time":0.06098263661},
{"learn":[4.748763714],"iteration":798,"passed_time":0.2411297398,"remaining_time":0.06065967171},
{"learn":[4.747965278],"iteration":799,"passed_time":0.241343792,"remaining_time":0.06033594801},
{"learn":[4.747028519],"iteration":800,"passed_time":0.2415495105,"remaining_time":0.06001042771},
{"learn":[4.745969025],"iteration":801,"passed_time":0.2417523122,"remaining_time":0.05968448606},
{"learn":[4.744938989],"iteration":802,"passed_time":0.2419559889,"remaining_time":0.05935906578},
{"learn":[4.744040695],"iteration":803,"passed_time":0.2421667077,"remaining_time":0.05903566505},
{"learn":[4.743606735],"iteration":804,"passed_time":0.2423602589,"remaining_time":0.05870838569},
{"learn":[4.741801626],"iteration":805,"passed_time":0.2425733527,"remaining_time":0.05838614198},
{"learn":[4.740897949],"iteration":806,"passed_time":0.2427977805,"remaining_time":0.05806687935},
{"learn":[4.739767243],"iteration":807,"passed_time":0.2430031656,"remaining_time":0.05774332649},
{"learn":[4.738792175],"iteration":808,"passed_time":0.2432051756,"remaining_time":0.0574192689},
{"learn":[4.73779447],"iteration":809,"passed_time":0.2434357287,"remaining_time":0.05710220796},
{"learn":[4.736993967],"iteration":810,"passed_time":0.243638572,"remaining_time":0.05677890273},
{"learn":[4.73578358],"iteration":811,"passed_time":0.2438735419,"remaining_time":0.05646333237},
{"learn":[4.73514337],"iteration":812,"passed_time":0.2441475971,"remaining_time":0.05615695039},
{"learn":[4.734382412],"iteration":813,"passed_time":0.2443783169,"remaining_time":0.05584074562},
{"learn":[4.733844381],"iteration":814,"passed_time":0.2445912857,"remaining_time":0.0555207213},
{"learn":[4.732733005],"iteration":815,"passed_time":0.2447961708,"remaining_time":0.05519913656},
{"learn":[4.731828857],"iteration":816,"passed_time":0.2450153067,"remaining_time":0.05488102952},
{"learn":[4.731611224],"iteration":817,"passed_time":0.2452209001,"remaining_time":0.05456015138},
{"learn":[4.731268767],"iteration":818,"passed_time":0.2454597453,"remaining_time":0.05424690341},
{"learn":[4.730839983],"iteration":819,"passed_time":0.2456721308,"remaining_time":0.0539280287},
{"learn":[4.72965704],"iteration":820,"passed_time":0.2458921416,"remaining_time":0.05361107594},
{"learn":[4.728471572],"iteration":821,"passed_time":0.246121778,"remaining_time":0.0532964434},
{"learn":[4.727101182],"iteration":822,"passed_time":0.2463641649,"remaining_time":0.05298475965},
{"learn":[4.725727071],"iteration":823,"passed_time":0.2465692584,"remaining_time":0.05266527849},
{"learn":[4.725016004],"iteration":824,"passed_time":0.2467719767,"remaining_time":0.05234557082},
{"learn":[4.724072281],"iteration":825,"passed_time":0.2469848622,"remaining_time":0.05202828817},
{"learn":[4.723422916],"iteration":826,"passed_time":0.2472351663,"remaining_time":0.05171908557},
{"learn":[4.722070043],"iteration":827,"passed_time":0.2474549688,"remaining_time":0.05140368917},
{"learn":[4.721334757],"iteration":828,"passed_time":0.2476623124,"remaining_time":0.05108595345},
{"learn":[4.719899937],"iteration":829,"passed_time":0.2478837816,"remaining_time":0.05077137696},
{"learn":[4.719277061],"iteration":830,"passed_time":0.2481117096,"remaining_time":0.05045833804},
{"learn":[4.718667224],"iteration":831,"passed_time":0.2483323454,"remaining_time":0.05014403129},
{"learn":[4.717915724],"iteration":832,"passed_time":0.2485203547,"remaining_time":0.04982340845},
{"learn":[4.717367238],"iteration":833,"passed_time":0.2487496577,"remaining_time":0.04951132276},
{"learn":[4.716253233],"iteration":834,"passed_time":0.2489614182,"remaining_time":0.04919596886},
{"learn":[4.715789535],"iteration":835,"passed_time":0.2491633031,"remaining_time":0.0488789255},
{"learn":[4.714992682],"iteration":836,"passed_time":0.2494705266,"remaining_time":0.04858267126},
{"learn":[4.714469847],"iteration":837,"passed_time":0.2497052466,"remaining_time":0.04827237464},
{"learn":[4.712994482],"iteration":838,"passed_time":0.2499950942,"remaining_time":0.04797283691},
{"learn":[4.712173864],"iteration":839,"passed_time":0.2501917289,"remaining_time":0.04765556741},
{"learn":[4.711669323],"iteration":840,"passed_time":0.2504102397,"remaining_time":0.04734272071},
{"learn":[4.711544569],"iteration":841,"passed_time":0.2506740027,"remaining_time":0.04703858959},
{"learn":[4.711017443],"iteration":842,"passed_time":0.2509010556,"remaining_time":0.04672771736},
{"learn":[4.710392833],"iteration":843,"passed_time":0.2511516097,"remaining_time":0.04642138757},
{"learn":[4.709956038],"iteration":844,"passed_time":0.251366912,"remaining_time":0.04610872349},
{"learn":[4.708879303],"iteration":845,"passed_time":0.2516210912,"remaining_time":0.04580336648},
{"learn":[4.708104962],"iteration":846,"passed_time":0.2518192676,"remaining_time":0.0454880141},
{"learn":[4.707648031],"iteration":847,"passed_time":0.2520620296,"remaining_time":0.04518092984},
{"learn":[4.7070034],"iteration":848,"passed_time":0.2522967912,"remaining_time":0.04487257417},
{"learn":[4.706032324],"iteration":849,"passed_time":0.2525215523,"remaining_time":0.04456262688},
{"learn":[4.705109999],"iteration":850,"passed_time":0.2527605224,"remaining_time":0.04425536762},
{"learn":[4.704082869],"iteration":851,"passed_time":0.2529764081,"remaining_time":0.04394425868},
{"learn":[4.703273299],"iteration":852,"passed_time":0.2531984607,"remaining_time":0.04363443579},
{"learn":[4.702239187],"iteration":853,"passed_time":0.2534263053,"remaining_time":0.04332580864},
{"learn":[4.701953272],"iteration":854,"passed_time":0.2536550666,"remaining_time":0.04301752592},
{"learn":[4.701302607],"iteration":855,"passed_time":0.2538632436,"remaining_time":0.0427059662},
{"learn":[4.700482446],"iteration":856,"passed_time":0.2540661702,"remaining_time":0.0423937717},
{"learn":[4.699736199],"iteration":857,"passed_time":0.2542905563,"remaining_time":0.04208538345},
{"learn":[4.69899539],"iteration":858,"passed_time":0.2545241929,"remaining_time":0.04177870919},
{"learn":[4.698243073],"iteration":859,"passed_time":0.2547499957,"remaining_time":0.04147092953},
{"learn":[4.698209932],"iteration":860,"passed_time":0.2548347499,"remaining_time":0.04114056937},
{"learn":[4.697870801],"iteration":861,"passed_time":0.2550412601,"remaining_time":0.04083027133},
{"learn":[4.69664589],"iteration":862,"passed_time":0.255296481,"remaining_time":0.04052794658},
{"learn":[4.69573773],"iteration":863,"passed_time":0.255505658,"remaining_time":0.0402184832},
{"learn":[4.695090103],"iteration":864,"passed_time":0.2557167934,"remaining_time":0.03990955735},
{"learn":[4.693901139],"iteration":865,"passed_time":0.2559154699,"remaining_time":0.03959892952},
{"learn":[4.693446568],"iteration":866,"passed_time":0.2561274387,"remaining_time":0.03929059901},
{"learn":[4.692510896],"iteration":867,"passed_time":0.2563261152,"remaining_time":0.03898046913},
{"learn":[4.690747828],"iteration":868,"passed_time":0.256517583,"remaining_time":0.03866950905},
{"learn":[4.689888563],"iteration":869,"passed_time":0.256728135,"remaining_time":0.03836167535},
{"learn":[4.689702963],"iteration":870,"passed_time":0.2569271865,"remaining_time":0.03805236172},
{"learn":[4.6889871],"iteration":871,"passed_time":0.2571466557,"remaining_time":0.03774629808},
{"learn":[4.688295659],"iteration":872,"passed_time":0.257348749,"remaining_time":0.03743790507},
{"learn":[4.68775527],"iteration":873,"passed_time":0.2575500506,"remaining_time":0.03712964116},
{"learn":[4.686960555],"iteration":874,"passed_time":0.2577951877,"remaining_time":0.03682788396},
{"learn":[4.68565346],"iteration":875,"passed_time":0.2580364913,"remaining_time":0.03652571338},
{"learn":[4.685333507],"iteration":876,"passed_time":0.2582498768,"remaining_time":0.03621976608},
{"learn":[4.684816365],"iteration":877,"passed_time":0.2584491783,"remaining_time":0.03591207262},
{"learn":[4.683827439],"iteration":878,"passed_time":0.2586578553,"remaining_time":0.03560591637},
{"learn":[4.683371007],"iteration":879,"passed_time":0.2588808246,"remaining_time":0.03530193063},
{"learn":[4.681833509],"iteration":880,"passed_time":0.2590739592,"remaining_time":0.03499409891},
{"learn":[4.680889935],"iteration":881,"passed_time":0.2592937617,"remaining_time":0.0346900951},
{"learn":[4.679303311],"iteration":882,"passed_time":0.2595022303,"remaining_time":0.03438478024},
{"learn":[4.679196139],"iteration":883,"passed_time":0.2596909063,"remaining_time":0.03407708725},
{"learn":[4.677902114],"iteration":884,"passed_time":0.2599285014,"remaining_time":0.03377601995},
{"learn":[4.677871425],"iteration":885,"passed_time":0.2599727952,"remaining_time":0.03345022422},
{"learn":[4.677348891],"iteration":886,"passed_time":0.2602058067,"remaining_time":0.03314910503},
{"learn":[4.67683957],"iteration":887,"passed_time":0.2604222341,"remaining_time":0.03284604754},
{"learn":[4.676164435],"iteration":888,"passed_time":0.260630411,"remaining_time":0.03254215481},
{"learn":[4.674700451],"iteration":889,"passed_time":0.2608452966,"remaining_time":0.03223930633},
{"learn":[4.674289353],"iteration":890,"passed_time":0.2610653908,"remaining_time":0.03193729248},
{"learn":[4.673549187],"iteration":891,"passed_time":0.261264984,"remaining_time":0.03163298013},
{"learn":[4.672533321],"iteration":892,"passed_time":0.261481328,"remaining_time":0.03133090941},
{"learn":[4.671853333],"iteration":893,"passed_time":0.2616771711,"remaining_time":0.0310265997},
{"learn":[4.670865583],"iteration":894,"passed_time":0.261878181,"remaining_time":0.03072313855},
{"learn":[4.670524619],"iteration":895,"passed_time":0.2620867329,"remaining_time":0.0304207815},
{"learn":[4.670399063],"iteration":896,"passed_time":0.2623062855,"remaining_time":0.03011989677},
{"learn":[4.669735317],"iteration":897,"passed_time":0.2625213794,"remaining_time":0.02981868675},
{"learn":[4.668724169],"iteration":898,"passed_time":0.2627335565,"remaining_time":0.02951734061},
{"learn":[4.667459904],"iteration":899,"passed_time":0.262958276,"remaining_time":0.02921758622},
{"learn":[4.666779978],"iteration":900,"passed_time":0.263228331,"remaining_time":0.02892297976},
{"learn":[4.665290864],"iteration":901,"passed_time":0.2634363413,"remaining_time":0.02862168674},
{"learn":[4.664735559],"iteration":902,"passed_time":0.263654852,"remaining_time":0.02832172829},
{"learn":[4.663512443],"iteration":903,"passed_time":0.2639111147,"remaining_time":0.02802595908},
{"learn":[4.663013644],"iteration":904,"passed_time":0.2641320006,"remaining_time":0.0277265636},
{"learn":[4.66108808],"iteration":905,"passed_time":0.2643392608,"remaining_time":0.02742592772},
{"learn":[4.659936592],"iteration":906,"passed_time":0.2645788143,"remaining_time":0.02712880897},
{"learn":[4.659192896],"iteration":907,"passed_time":0.2648602866,"remaining_time":0.02683606428},
{"learn":[4.658097221],"iteration":908,"passed_time":0.2650761722,"remaining_time":0.02653677852},
{"learn":[4.657602077],"iteration":909,"passed_time":0.2652795156,"remaining_time":0.02623643561},
{"learn":[4.65691977],"iteration":910,"passed_time":0.2654857341,"remaining_time":0.02593658654},
{"learn":[4.656230158],"iteration":911,"passed_time":0.2656969529,"remaining_time":0.02563742528},
{"learn":[4.655705079],"iteration":912,"passed_time":0.2658991712,"remaining_time":0.02533759901},
{"learn":[4.655172286],"iteration":913,"passed_time":0.2661130568,"remaining_time":0.02503908411},
{"learn":[4.654992944],"iteration":914,"passed_time":0.266321067,"remaining_time":0.02474020841},
{"learn":[4.654425172],"iteration":915,"passed_time":0.2665147016,"remaining_time":0.02444021281},
{"learn":[4.653538616],"iteration":916,"passed_time":0.2667196284,"remaining_time":0.02414147127},
{"learn":[4.652696259],"iteration":917,"passed_time":0.2669519315,"remaining_time":0.0238453795},
{"learn":[4.652066563],"iteration":918,"passed_time":0.2671740258,"remaining_time":0.02354852676},
{"learn":[4.65159162],"iteration":919,"passed_time":0.2673856196,"remaining_time":0.02325092344},
{"learn":[4.651382226],"iteration":920,"passed_time":0.2676189228,"remaining_time":0.02295536905},
{"learn":[4.650612639],"iteration":921,"passed_time":0.2678366835,"remaining_time":0.02265863483},
{"learn":[4.649776317],"iteration":922,"passed_time":0.2680467772,"remaining_time":0.02236143212},
{"learn":[4.647726739],"iteration":923,"passed_time":0.2682735384,"remaining_time":0.02206578888},
{"learn":[4.647312244],"iteration":924,"passed_time":0.2685242591,"remaining_time":0.02177223723},
{"learn":[4.646465017],"iteration":925,"passed_time":0.2687221856,"remaining_time":0.02147455911},
{"learn":[4.64533902],"iteration":926,"passed_time":0.2689730313,"remaining_time":0.02118126352},
{"learn":[4.644523945],"iteration":927,"passed_time":0.2692203769,"remaining_time":0.02088778786},
{"learn":[4.643932186],"iteration":928,"passed_time":0.2694418045,"remaining_time":0.0205924307},
{"learn":[4.643112184],"iteration":929,"passed_time":0.2696663155,"remaining_time":0.02029746461},
{"learn":[4.642563299],"iteration":930,"passed_time":0.2699044523,"remaining_time":0.02000365973},
{"learn":[4.641763215],"iteration":931,"passed_time":0.2701244632,"remaining_time":0.01970865182},
{"learn":[4.640953194],"iteration":932,"passed_time":0.2703487659,"remaining_time":0.01941411288},
{"learn":[4.640790508],"iteration":933,"passed_time":0.2705586929,"remaining_time":0.01911870849},
{"learn":[4.639991894],"iteration":934,"passed_time":0.2707671199,"remaining_time":0.01882338267},
{"learn":[4.639339219],"iteration":935,"passed_time":0.2709792554,"remaining_time":0.01852849609},
{"learn":[4.638419181],"iteration":936,"passed_time":0.2711963078,"remaining_time":0.01823411674},
{"learn":[4.637590291],"iteration":937,"passed_time":0.2714227356,"remaining_time":0.01794052197},
{"learn":[4.63700092],"iteration":938,"passed_time":0.2716559971,"remaining_time":0.01764751419},
{"learn":[4.636422225],"iteration":939,"passed_time":0.2718896337,"remaining_time":0.01735465747},
{"learn":[4.636143022],"iteration":940,"passed_time":0.2721160198,"remaining_time":0.01706147202},
{"learn":[4.635073582],"iteration":941,"passed_time":0.2723577401,"remaining_time":0.01676937253},
{"learn":[4.634929354],"iteration":942,"passed_time":0.2725601668,"remaining_time":0.01647500478},
{"learn":[4.634459802],"iteration":943,"passed_time":0.2727663853,"remaining_time":0.01618105675},
{"learn":[4.634361034],"iteration":944,"passed_time":0.2729692703,"remaining_time":0.01588710039},
{"learn":[4.634261064],"iteration":945,"passed_time":0.2731973649,"remaining_time":0.01559477559},
{"learn":[4.633550983],"iteration":946,"passed_time":0.2733934579,"remaining_time":0.01530079543},
{"learn":[4.632394626],"iteration":947,"passed_time":0.2736070518,"remaining_time":0.01500798174},
{"learn":[4.63170274],"iteration":948,"passed_time":0.2738299378,"remaining_time":0.01471583438},
{"learn":[4.630919349],"iteration":949,"passed_time":0.2740746165,"remaining_time":0.01442497982},
{"learn":[4.630107668],"iteration":950,"passed_time":0.2743077114,"remaining_time":0.01413362551},
{"learn":[4.629345498],"iteration":951,"passed_time":0.2745246804,"remaining_time":0.01384158053},
{"learn":[4.627262917],"iteration":952,"passed_time":0.2747333157,"remaining_time":0.0135492821},
{"learn":[4.626161896],"iteration":953,"passed_time":0.2750104128,"remaining_time":0.01326046015},
{"learn":[4.624878939],"iteration":954,"passed_time":0.2752319654,"remaining_time":0.01296904549},
{"learn":[4.623983796],"iteration":955,"passed_time":0.2754461426,"remaining_time":0.01267743753},
{"learn":[4.623494575],"iteration":956,"passed_time":0.2756640284,"remaining_time":0.01238615801},
{"learn":[4.622532026],"iteration":957,"passed_time":0.2758692468,"remaining_time":0.01209447637},
{"learn":[4.621422829],"iteration":958,"passed_time":0.2760588812,"remaining_time":0.01180230879},
{"learn":[4.620687301],"iteration":959,"passed_time":0.2762698916,"remaining_time":0.01151124548},
{"learn":[4.620465764],"iteration":960,"passed_time":0.2765034865,"remaining_time":0.01122126532},
{"learn":[4.620083249],"iteration":961,"passed_time":0.2767132885,"remaining_time":0.01093046254},
{"learn":[4.619347375],"iteration":962,"passed_time":0.27691334,"remaining_time":0.01063945336},
{"learn":[4.618757921],"iteration":963,"passed_time":0.2771173501,"remaining_time":0.01034878071},
{"learn":[4.618678824],"iteration":964,"passed_time":0.2773239853,"remaining_time":0.01005838289},
{"learn":[4.617571325],"iteration":965,"passed_time":0.2775312872,"remaining_time":0.009768181952},
{"learn":[4.616744738],"iteration":966,"passed_time":0.2777449228,"remaining_time":0.009478368616},
{"learn":[4.616062865],"iteration":967,"passed_time":0.2779768092,"remaining_time":0.009189316008},
{"learn":[4.615469056],"iteration":968,"passed_time":0.2782150293,"remaining_time":0.008900584013},
{"learn":[4.614142182],"iteration":969,"passed_time":0.2784975849,"remaining_time":0.008613327369},
{"learn":[4.61355511],"iteration":970,"passed_time":0.2787193876,"remaining_time":0.008324265952},
{"learn":[4.613147425],"iteration":971,"passed_time":0.278951524,"remaining_time":0.00803564061},
{"learn":[4.612413129],"iteration":972,"passed_time":0.2791835355,"remaining_time":0.007747127912},
{"learn":[4.61175764],"iteration":973,"passed_time":0.2793958376,"remaining_time":0.007458205111},
{"learn":[4.611107139],"iteration":974,"passed_time":0.2796242656,"remaining_time":0.007169852963},
{"learn":[4.610657621],"iteration":975,"passed_time":0.27988257,"remaining_time":0.006882358279},
{"learn":[4.609599788],"iteration":976,"passed_time":0.280098789,"remaining_time":0.006593932597},
{"learn":[4.609151221],"iteration":977,"passed_time":0.2803269669,"remaining_time":0.006305923592},
{"learn":[4.608627407],"iteration":978,"passed_time":0.2805446444,"remaining_time":0.006017811575},
{"learn":[4.607191341],"iteration":979,"passed_time":0.2807444459,"remaining_time":0.005729478487},
{"learn":[4.607037481],"iteration":980,"passed_time":0.2809477893,"remaining_time":0.005441394491},
{"learn":[4.606337488],"iteration":981,"passed_time":0.2811622999,"remaining_time":0.005153687777},
{"learn":[4.605827366],"iteration":982,"passed_time":0.2813664349,"remaining_time":0.004865950553},
{"learn":[4.605066862],"iteration":983,"passed_time":0.2815784454,"remaining_time":0.004578511307},
{"learn":[4.604809393],"iteration":984,"passed_time":0.2818027481,"remaining_time":0.004291412408},
{"learn":[4.604551179],"iteration":985,"passed_time":0.2820241341,"remaining_time":0.00400439947},
{"learn":[4.604401493],"iteration":986,"passed_time":0.2822684378,"remaining_time":0.003717821369},
{"learn":[4.602960605],"iteration":987,"passed_time":0.2824865736,"remaining_time":0.003431011015},
{"learn":[4.602550465],"iteration":988,"passed_time":0.2827268354,"remaining_time":0.003144585632},
{"learn":[4.602032229],"iteration":989,"passed_time":0.2829557217,"remaining_time":0.002858138603},
{"learn":[4.601222679],"iteration":990,"passed_time":0.2831541065,"remaining_time":0.002571530735},
{"learn":[4.600558533],"iteration":991,"passed_time":0.2833786593,"remaining_time":0.002285311768},
{"learn":[4.600105891],"iteration":992,"passed_time":0.2836188795,"remaining_time":0.001999327449},
{"learn":[4.599338023],"iteration":993,"passed_time":0.2838398904,"remaining_time":0.001713319258},
{"learn":[4.598636072],"iteration":994,"passed_time":0.2841170708,"remaining_time":0.001427723974},
{"learn":[4.598070443],"iteration":995,"passed_time":0.2843529991,"remaining_time":0.001141979916},
{"learn":[4.598043758],"iteration":996,"passed_time":0.284500048,"remaining_time":0.000856068349},
{"learn":[4.597624197],"iteration":997,"passed_time":0.2847205589,"remaining_time":0.0005705822823},
{"learn":[4.597219678],"iteration":998,"passed_time":0.284939653,"remaining_time":0.0002852248779},
{"learn":[4.596450536],"iteration":999,"passed_time":0.285155622,"remaining_time":0}
]}